{
  "type": "Feature",
  "properties": {
    "gn:admin1_code":"08",
    "gn:asciiname":"Nzara",
    "gn:country_code":"ZW",
    "gn:dem":917,
    "gn:feature_class":"P",
    "gn:feature_code":"PPL",
    "gn:name":"Nzara",
    "gn:population":0,
    "gn:timezone":"Africa/Harare",
    "iso:country":"ZW",
    "wof:name":"Nzara",
    "wof:placetype":"locality"
},
  "geometry": {"coordinates":[31.70798,-19.79127],"type":"Point"}
}