{
  "type": "Feature",
  "properties": {
    "gn:admin1_code":"8.0",
    "gn:asciiname":"Felixburg",
    "gn:country_code":"ZW",
    "gn:dem":1510,
    "gn:feature_class":"P",
    "gn:feature_code":"PPL",
    "gn:name":"Felixburg",
    "gn:population":0,
    "gn:timezone":"Africa/Harare",
    "iso:country":"ZW",
    "name:bar_x_preferred":[
        "Felixburg"
    ],
    "wof:name":"Felixburg",
    "wof:placetype":"locality"
},
  "geometry": {"coordinates":[30.84175,-19.43008],"type":"Point"}
}