{
  "type": "Feature",
  "properties": {
    "iso:country":"ZW",
    "name:afr_x_preferred":[
        "Shurugwi"
    ],
    "name:bar_x_preferred":[
        "Selukwe"
    ],
    "name:dan_x_preferred":[
        "Shurugwi"
    ],
    "name:deu_x_preferred":[
        "Shurugwi"
    ],
    "name:eng_x_preferred":[
        "Shurugwi"
    ],
    "name:fra_x_preferred":[
        "Shurugwi"
    ],
    "name:gle_x_preferred":[
        "Shurugwi"
    ],
    "name:ita_x_preferred":[
        "Shurugwi"
    ],
    "name:jpn_x_preferred":[
        "\u30b7\u30e5\u30eb\u30b0\u30a6\u30a3"
    ],
    "name:kor_x_preferred":[
        "\uc288\ub8e8\uadc0"
    ],
    "name:nld_x_preferred":[
        "Shurugwi"
    ],
    "name:pol_x_preferred":[
        "Shurugwi"
    ],
    "name:ron_x_preferred":[
        "Shurugwi"
    ],
    "name:rus_x_preferred":[
        "\u0428\u0443\u0440\u0443\u0433\u0432\u0438"
    ],
    "name:srp_x_preferred":[
        "\u0428\u0443\u0440\u0443\u0433\u0432\u0438"
    ],
    "name:unk_x_variant":[
        "Churugwi"
    ],
    "name:urd_x_preferred":[
        "\u0634\u0648\u0631\u0648\u06af\u0648\u06cc"
    ],
    "name:zho_x_preferred":[
        "\u8212\u9b6f\u572d"
    ],
    "qs:gn_country":"ZW",
    "qs:gn_fcode":"PPL",
    "qs:gn_pop":17075,
    "qs:name":"Shurugwi",
    "qs:name_adm0":"Zimbabwe",
    "qs:name_adm1":"Midlands",
    "qs:photos":0,
    "qs:photos_1k":0,
    "qs:photos_9k":0,
    "qs:photos_9r":0,
    "qs:photos_all":0,
    "qs:photos_sr":0,
    "qs:placetype":"Town",
    "qs:pop_sr":"6",
    "qs:woe_adm0":23425004,
    "wd:wordcount":913,
    "wof:name":"Shurugwi",
    "wof:placetype":"locality",
    "wof:population":17075
},
  "geometry": {"coordinates":[30.00589,-19.67016],"type":"Point"}
}