{
  "type": "Feature",
  "properties": {
    "gn:admin1_code":"6.0",
    "gn:asciiname":"Sibaba",
    "gn:country_code":"ZW",
    "gn:dem":972,
    "gn:feature_class":"P",
    "gn:feature_code":"PPL",
    "gn:name":"Sibaba",
    "gn:population":0,
    "gn:timezone":"Africa/Harare",
    "iso:country":"ZW",
    "wof:name":"Sibaba",
    "wof:placetype":"locality"
},
  "geometry": {"coordinates":[27.68249,-19.05056],"type":"Point"}
}