{
  "type": "Feature",
  "properties": {
    "gn:admin1_code":"4.0",
    "gn:asciiname":"Kwaramba",
    "gn:country_code":"ZW",
    "gn:dem":1553,
    "gn:feature_class":"P",
    "gn:feature_code":"PPL",
    "gn:name":"Kwaramba",
    "gn:population":0,
    "gn:timezone":"Africa/Harare",
    "iso:country":"ZW",
    "wof:name":"Kwaramba",
    "wof:placetype":"locality"
},
  "geometry": {"coordinates":[31.74421,-18.33603],"type":"Point"}
}