{
  "type": "Feature",
  "properties": {
    "gn:admin1_code":"4.0",
    "gn:asciiname":"Inoro",
    "gn:country_code":"ZW",
    "gn:dem":1430,
    "gn:feature_class":"P",
    "gn:feature_code":"PPL",
    "gn:name":"Inoro",
    "gn:population":0,
    "gn:timezone":"Africa/Harare",
    "iso:country":"ZW",
    "name:eng_x_preferred":[
        "Inoro"
    ],
    "wof:name":"Inoro",
    "wof:placetype":"locality"
},
  "geometry": {"coordinates":[31.51667,-18.46667],"type":"Point"}
}