{
  "type": "Feature",
  "properties": {
    "gn:admin1_code":"08",
    "gn:asciiname":"Gogode",
    "gn:country_code":"ZW",
    "gn:dem":1040,
    "gn:feature_class":"P",
    "gn:feature_code":"PPL",
    "gn:name":"Gogode",
    "gn:population":0,
    "gn:timezone":"Africa/Harare",
    "iso:country":"ZW",
    "wof:name":"Gogode",
    "wof:placetype":"locality"
},
  "geometry": {"coordinates":[31.55598,-19.67755],"type":"Point"}
}