{
  "type": "Feature",
  "properties": {
    "gn:country":"ZW",
    "gn:fcode":"PPL",
    "gn:population":4852,
    "iso:country":"ZW",
    "name:ast_x_preferred":[
        "Nyanga"
    ],
    "name:ceb_x_preferred":[
        "Nyanga"
    ],
    "name:deu_x_preferred":[
        "Nyanga"
    ],
    "name:eng_x_preferred":[
        "Nyanga"
    ],
    "name:fra_x_preferred":[
        "Nyanga"
    ],
    "name:heb_x_preferred":[
        "\u05e0\u05d9\u05d0\u05e0\u05d2\u05d4"
    ],
    "name:hun_x_preferred":[
        "Nyanga"
    ],
    "name:ita_x_preferred":[
        "Nyanga"
    ],
    "name:nld_x_preferred":[
        "Nyanga"
    ],
    "name:nob_x_preferred":[
        "Nyanga"
    ],
    "name:por_x_preferred":[
        "Nyhanga"
    ],
    "name:sna_x_preferred":[
        "Nyanga"
    ],
    "name:srp_x_preferred":[
        "\u040a\u0430\u043d\u0433\u0430"
    ],
    "name:tur_x_preferred":[
        "Nyanga"
    ],
    "name:zho_x_preferred":[
        "\u5c3c\u63da\u52a0"
    ],
    "name:zul_x_preferred":[
        "Nyanga"
    ],
    "qs:name":"Nyanga",
    "qs:photos_9r":0,
    "qs:photos_sr":0,
    "qs:pop_sr":"4",
    "wd:wordcount":79,
    "wof:name":"Nyanga",
    "wof:placetype":"locality",
    "wof:population":4852
},
  "geometry": {"coordinates":[32.75,-18.21667],"type":"Point"}
}