{
  "type": "Feature",
  "properties": {
    "gn:admin1_code":"1.0",
    "gn:asciiname":"Mhaka",
    "gn:country_code":"ZW",
    "gn:dem":989,
    "gn:feature_class":"P",
    "gn:feature_code":"PPL",
    "gn:name":"Mhaka",
    "gn:population":0,
    "gn:timezone":"Africa/Harare",
    "iso:country":"ZW",
    "wof:name":"Mhaka",
    "wof:placetype":"locality"
},
  "geometry": {"coordinates":[31.80709,-19.46646],"type":"Point"}
}