{
  "type": "Feature",
  "properties": {
    "gn:admin1_code":"10.0",
    "gn:asciiname":"Kaseke",
    "gn:country_code":"ZW",
    "gn:dem":1421,
    "gn:feature_class":"P",
    "gn:feature_code":"PPL",
    "gn:name":"Kaseke",
    "gn:population":0,
    "gn:timezone":"Africa/Harare",
    "iso:country":"ZW",
    "wof:name":"Kaseke",
    "wof:placetype":"locality"
},
  "geometry": {"coordinates":[31.05256,-18.01705],"type":"Point"}
}