{
  "type": "Feature",
  "properties": {
    "gn:admin1_code":"1.0",
    "gn:asciiname":"Ruzvidzo",
    "gn:country_code":"ZW",
    "gn:dem":870,
    "gn:feature_class":"P",
    "gn:feature_code":"PPL",
    "gn:name":"Ruzvidzo",
    "gn:population":0,
    "gn:timezone":"Africa/Harare",
    "iso:country":"ZW",
    "wof:name":"Ruzvidzo",
    "wof:placetype":"locality"
},
  "geometry": {"coordinates":[31.87745,-19.31938],"type":"Point"}
}