{
  "type": "Feature",
  "properties": {
    "gn:admin1_code":"6.0",
    "gn:asciiname":"Segogo",
    "gn:country_code":"ZW",
    "gn:dem":1185,
    "gn:feature_class":"P",
    "gn:feature_code":"PPL",
    "gn:name":"Segogo",
    "gn:population":0,
    "gn:timezone":"Africa/Harare",
    "iso:country":"ZW",
    "wof:name":"Segogo",
    "wof:placetype":"locality"
},
  "geometry": {"coordinates":[27.79856,-19.964],"type":"Point"}
}