{
  "type": "Feature",
  "properties": {
    "gn:admin1_code":"6.0",
    "gn:asciiname":"Somqibe",
    "gn:country_code":"ZW",
    "gn:dem":1074,
    "gn:feature_class":"P",
    "gn:feature_code":"PPL",
    "gn:name":"Somqibe",
    "gn:population":0,
    "gn:timezone":"Africa/Harare",
    "iso:country":"ZW",
    "name:und_x_variant":[
        "Somquibe",
        "Somqibe"
    ],
    "wof:name":"Somqibe",
    "wof:placetype":"locality"
},
  "geometry": {"coordinates":[27.68639000000001,-19.69181],"type":"Point"}
}