{
  "type": "Feature",
  "properties": {
    "gn:admin1_code":"1.0",
    "gn:asciiname":"Mateverere",
    "gn:country_code":"ZW",
    "gn:dem":824,
    "gn:feature_class":"P",
    "gn:feature_code":"PPL",
    "gn:name":"Mateverere",
    "gn:population":0,
    "gn:timezone":"Africa/Harare",
    "iso:country":"ZW",
    "wof:name":"Mateverere",
    "wof:placetype":"locality"
},
  "geometry": {"coordinates":[31.97148,-19.30985],"type":"Point"}
}