{
  "type": "Feature",
  "properties": {
    "gn:admin1_code":"5.0",
    "gn:asciiname":"Kakoma",
    "gn:country_code":"ZW",
    "gn:dem":1165,
    "gn:feature_class":"P",
    "gn:feature_code":"PPL",
    "gn:name":"Kakoma",
    "gn:population":0,
    "gn:timezone":"Africa/Harare",
    "iso:country":"ZW",
    "name:eng_x_preferred":[
        "Kakoma"
    ],
    "wof:name":"Kakoma",
    "wof:placetype":"locality"
},
  "geometry": {"coordinates":[29.64597,-16.38284],"type":"Point"}
}