{
  "type": "Feature",
  "properties": {
    "gn:admin1_code":"6.0",
    "gn:asciiname":"Mapilibomvu",
    "gn:country_code":"ZW",
    "gn:dem":1009,
    "gn:feature_class":"P",
    "gn:feature_code":"PPL",
    "gn:name":"Mapilibomvu",
    "gn:population":0,
    "gn:timezone":"Africa/Harare",
    "iso:country":"ZW",
    "wof:name":"Mapilibomvu",
    "wof:placetype":"locality"
},
  "geometry": {"coordinates":[27.71544,-19.40434],"type":"Point"}
}