{
  "type": "Feature",
  "properties": {
    "gn:admin1_code":"6.0",
    "gn:asciiname":"Lusulu",
    "gn:country_code":"ZW",
    "gn:dem":981,
    "gn:feature_class":"P",
    "gn:feature_code":"PPL",
    "gn:name":"Lusulu",
    "gn:population":0,
    "gn:timezone":"Africa/Harare",
    "iso:country":"ZW",
    "name:eng_x_preferred":[
        "Lusulu"
    ],
    "name:eng_x_variant":[
        "Lusulu Settlement"
    ],
    "wof:name":"Lusulu",
    "wof:placetype":"locality"
},
  "geometry": {"coordinates":[27.83478,-18.06378],"type":"Point"}
}