{
  "type": "Feature",
  "properties": {
    "gn:admin1_code":"8.0",
    "gn:asciiname":"Mutumbwi",
    "gn:country_code":"ZW",
    "gn:dem":836,
    "gn:feature_class":"P",
    "gn:feature_code":"PPL",
    "gn:name":"Mutumbwi",
    "gn:population":0,
    "gn:timezone":"Africa/Harare",
    "iso:country":"ZW",
    "wof:name":"Mutumbwi",
    "wof:placetype":"locality"
},
  "geometry": {"coordinates":[31.86427,-19.72599],"type":"Point"}
}