{
  "type": "Feature",
  "properties": {
    "gn:admin1_code":"1.0",
    "gn:asciiname":"Chief Mpungu",
    "gn:country_code":"ZW",
    "gn:dem":376,
    "gn:feature_class":"P",
    "gn:feature_code":"PPL",
    "gn:name":"Chief Mpungu",
    "gn:population":0,
    "gn:timezone":"Africa/Harare",
    "iso:country":"ZW",
    "name:eng_x_preferred":[
        "Chief Mpungu"
    ],
    "wof:name":"Chief Mpungu",
    "wof:placetype":"locality"
},
  "geometry": {"coordinates":[32.44205,-20.97117],"type":"Point"}
}