{
  "type": "Feature",
  "properties": {
    "gn:admin1_code":"7.0",
    "gn:asciiname":"Antenior",
    "gn:country_code":"ZW",
    "gn:dem":1004,
    "gn:feature_class":"P",
    "gn:feature_code":"PPL",
    "gn:name":"Antenior",
    "gn:population":0,
    "gn:timezone":"Africa/Harare",
    "iso:country":"ZW",
    "name:eng_x_preferred":[
        "Antenior"
    ],
    "wof:name":"Antenior",
    "wof:placetype":"locality"
},
  "geometry": {"coordinates":[29.03333,-20.98333],"type":"Point"}
}