{
  "type": "Feature",
  "properties": {
    "gn:admin1_code":"7.0",
    "gn:asciiname":"Mbalabala",
    "gn:country_code":"ZW",
    "gn:dem":1122,
    "gn:feature_class":"P",
    "gn:feature_code":"PPL",
    "gn:name":"Mbalabala",
    "gn:population":0,
    "gn:timezone":"Africa/Harare",
    "iso:country":"ZW",
    "name:eng_x_preferred":[
        "Mbalabala"
    ],
    "name:eng_x_variant":[
        "Balla Balla",
        "Balabala"
    ],
    "name:und_x_variant":[
        "Balabala",
        "Balla Balla"
    ],
    "wof:name":"Mbalabala",
    "wof:placetype":"locality"
},
  "geometry": {"coordinates":[29.04819,-20.44098],"type":"Point"}
}