{
  "type": "Feature",
  "properties": {
    "gn:admin1_code":"6.0",
    "gn:asciiname":"Pashu",
    "gn:country_code":"ZW",
    "gn:dem":868,
    "gn:feature_class":"P",
    "gn:feature_code":"PPL",
    "gn:name":"Pashu",
    "gn:population":0,
    "gn:timezone":"Africa/Harare",
    "iso:country":"ZW",
    "name:eng_x_preferred":[
        "Pashu"
    ],
    "name:eng_x_variant":[
        "Pashus"
    ],
    "name:und_x_variant":[
        "Pashus"
    ],
    "wof:name":"Pashu",
    "wof:placetype":"locality"
},
  "geometry": {"coordinates":[27.40922,-18.21278],"type":"Point"}
}