{
  "type": "Feature",
  "properties": {
    "gn:admin1_code":"1.0",
    "gn:asciiname":"Muchena",
    "gn:country_code":"ZW",
    "gn:dem":1057,
    "gn:feature_class":"P",
    "gn:feature_code":"PPL",
    "gn:name":"Muchena",
    "gn:population":0,
    "gn:timezone":"Africa/Harare",
    "iso:country":"ZW",
    "wof:name":"Muchena",
    "wof:placetype":"locality"
},
  "geometry": {"coordinates":[31.60212000000001,-19.09845],"type":"Point"}
}