{
  "type": "Feature",
  "properties": {
    "gn:admin1_code":"08",
    "gn:asciiname":"Nyamadzavo",
    "gn:country_code":"ZW",
    "gn:dem":790,
    "gn:feature_class":"P",
    "gn:feature_code":"PPL",
    "gn:name":"Nyamadzavo",
    "gn:population":0,
    "gn:timezone":"Africa/Harare",
    "iso:country":"ZW",
    "wof:name":"Nyamadzavo",
    "wof:placetype":"locality"
},
  "geometry": {"coordinates":[31.93955,-19.92834],"type":"Point"}
}