{
  "type": "Feature",
  "properties": {
    "gn:admin1_code":"1.0",
    "gn:asciiname":"Rambanapasi",
    "gn:country_code":"ZW",
    "gn:dem":1042,
    "gn:feature_class":"P",
    "gn:feature_code":"PPL",
    "gn:name":"Rambanapasi",
    "gn:population":0,
    "gn:timezone":"Africa/Harare",
    "iso:country":"ZW",
    "wof:name":"Rambanapasi",
    "wof:placetype":"locality"
},
  "geometry": {"coordinates":[31.62245,-19.14514],"type":"Point"}
}