{
  "type": "Feature",
  "properties": {
    "gn:admin1_code":"3.0",
    "gn:asciiname":"Vambe",
    "gn:country_code":"ZW",
    "gn:dem":1080,
    "gn:feature_class":"P",
    "gn:feature_code":"PPL",
    "gn:name":"Vambe",
    "gn:population":0,
    "gn:timezone":"Africa/Harare",
    "iso:country":"ZW",
    "name:eng_x_preferred":[
        "Vambe"
    ],
    "wof:name":"Vambe",
    "wof:placetype":"locality"
},
  "geometry": {"coordinates":[31.56876,-16.90045],"type":"Point"}
}