{
  "type": "Feature",
  "properties": {
    "gn:admin1_code":"08",
    "gn:asciiname":"Ziso",
    "gn:country_code":"ZW",
    "gn:dem":895,
    "gn:feature_class":"P",
    "gn:feature_code":"PPL",
    "gn:name":"Ziso",
    "gn:population":0,
    "gn:timezone":"Africa/Harare",
    "iso:country":"ZW",
    "wof:name":"Ziso",
    "wof:placetype":"locality"
},
  "geometry": {"coordinates":[31.84695,-19.74203],"type":"Point"}
}