{
  "type": "Feature",
  "properties": {
    "gn:admin1_code":"08",
    "gn:asciiname":"Beni",
    "gn:country_code":"ZW",
    "gn:dem":1028,
    "gn:feature_class":"P",
    "gn:feature_code":"PPL",
    "gn:name":"Beni",
    "gn:population":0,
    "gn:timezone":"Africa/Harare",
    "iso:country":"ZW",
    "wof:name":"Beni",
    "wof:placetype":"locality"
},
  "geometry": {"coordinates":[31.52834,-19.72678],"type":"Point"}
}