{
  "type": "Feature",
  "properties": {
    "gn:admin1_code":"08",
    "gn:asciiname":"Matombo",
    "gn:country_code":"ZW",
    "gn:dem":915,
    "gn:feature_class":"P",
    "gn:feature_code":"PPL",
    "gn:name":"Matombo",
    "gn:population":0,
    "gn:timezone":"Africa/Harare",
    "iso:country":"ZW",
    "wof:name":"Matombo",
    "wof:placetype":"locality"
},
  "geometry": {"coordinates":[31.80995,-19.70772],"type":"Point"}
}