{
  "type": "Feature",
  "properties": {
    "gn:admin1_code":"7.0",
    "gn:asciiname":"Bannockburn",
    "gn:country_code":"ZW",
    "gn:dem":1045,
    "gn:feature_class":"P",
    "gn:feature_code":"PPL",
    "gn:name":"Bannockburn",
    "gn:population":0,
    "gn:timezone":"Africa/Harare",
    "iso:country":"ZW",
    "name:bar_x_preferred":[
        "Bannockburn"
    ],
    "name:bul_x_preferred":[
        "\u0411\u0430\u043d\u044a\u043a\u0431\u044a\u0440\u043d"
    ],
    "name:ceb_x_preferred":[
        "Bannockburn"
    ],
    "name:deu_x_preferred":[
        "Bannockburn"
    ],
    "name:eng_x_preferred":[
        "Bannockburn"
    ],
    "name:epo_x_preferred":[
        "Bannockburn"
    ],
    "name:eus_x_preferred":[
        "Bannockburn"
    ],
    "name:fas_x_preferred":[
        "\u0628\u0627\u0646\u0648\u06a9\u0628\u0631\u0646"
    ],
    "name:fra_x_preferred":[
        "Bannockburn"
    ],
    "name:ita_x_preferred":[
        "Bannockburn"
    ],
    "name:nld_x_preferred":[
        "Bannockburn"
    ],
    "name:nno_x_preferred":[
        "Bannockburn"
    ],
    "name:nor_x_preferred":[
        "Bannockburn"
    ],
    "name:pol_x_preferred":[
        "Bannockburn"
    ],
    "name:por_x_preferred":[
        "Bannockburn"
    ],
    "name:slv_x_preferred":[
        "Bannockburn"
    ],
    "name:spa_x_preferred":[
        "Bannockburn"
    ],
    "name:swe_x_preferred":[
        "Bannockburn"
    ],
    "name:zho_x_preferred":[
        "\u73ed\u8bfa\u514b\u672c"
    ],
    "wof:name":"Bannockburn",
    "wof:placetype":"locality"
},
  "geometry": {"coordinates":[29.89899,-20.27841],"type":"Point"}
}