{
  "type": "Feature",
  "properties": {
    "gn:admin1_code":"7.0",
    "gn:asciiname":"Bannockburn",
    "gn:country_code":"ZW",
    "gn:dem":1045,
    "gn:feature_class":"P",
    "gn:feature_code":"PPL",
    "gn:name":"Bannockburn",
    "gn:population":0,
    "gn:timezone":"Africa/Harare",
    "iso:country":"ZW",
    "name:eng_x_preferred":[
        "Bannockburn"
    ],
    "wof:name":"Bannockburn",
    "wof:placetype":"locality"
},
  "geometry": {"coordinates":[29.89899,-20.27841],"type":"Point"}
}