{
  "type": "Feature",
  "properties": {
    "gn:admin1_code":"5.0",
    "gn:asciiname":"Makuti",
    "gn:country_code":"ZW",
    "gn:dem":1187,
    "gn:feature_class":"P",
    "gn:feature_code":"PPL",
    "gn:name":"Makuti",
    "gn:population":0,
    "gn:timezone":"Africa/Harare",
    "iso:country":"ZW",
    "name:bar_x_preferred":[
        "Makuti"
    ],
    "name:deu_x_preferred":[
        "Makuti"
    ],
    "name:eng_x_preferred":[
        "Makuti"
    ],
    "name:fra_x_preferred":[
        "Makuti"
    ],
    "wof:name":"Makuti",
    "wof:placetype":"locality"
},
  "geometry": {"coordinates":[29.25192,-16.31648],"type":"Point"}
}