{
  "type": "Feature",
  "properties": {
    "gn:admin1_code":"5.0",
    "gn:asciiname":"Samasuro Bunda II",
    "gn:country_code":"ZW",
    "gn:dem":1139,
    "gn:feature_class":"P",
    "gn:feature_code":"PPL",
    "gn:name":"Samasuro Bunda II",
    "gn:population":0,
    "gn:timezone":"Africa/Harare",
    "iso:country":"ZW",
    "name:eng_x_preferred":[
        "Samasuro Bunda II"
    ],
    "wof:name":"Samasuro Bunda II",
    "wof:placetype":"locality"
},
  "geometry": {"coordinates":[29.3266,-16.84378],"type":"Point"}
}