{
  "type": "Feature",
  "properties": {
    "gn:admin1_code":"6.0",
    "gn:asciiname":"Lubesi",
    "gn:country_code":"ZW",
    "gn:dem":1013,
    "gn:feature_class":"P",
    "gn:feature_code":"PPL",
    "gn:name":"Lubesi",
    "gn:population":0,
    "gn:timezone":"Africa/Harare",
    "iso:country":"ZW",
    "wof:name":"Lubesi",
    "wof:placetype":"locality"
},
  "geometry": {"coordinates":[27.19328,-19.62111],"type":"Point"}
}