{
  "type": "Feature",
  "properties": {
    "gn:admin1_code":"6.0",
    "gn:asciiname":"Nxuma",
    "gn:country_code":"ZW",
    "gn:dem":1018,
    "gn:feature_class":"P",
    "gn:feature_code":"PPL",
    "gn:name":"Nxuma",
    "gn:population":0,
    "gn:timezone":"Africa/Harare",
    "iso:country":"ZW",
    "wof:name":"Nxuma",
    "wof:placetype":"locality"
},
  "geometry": {"coordinates":[27.2254,-19.63914],"type":"Point"}
}