{
  "type": "Feature",
  "properties": {
    "gn:admin1_code":"08",
    "gn:asciiname":"Zeka",
    "gn:country_code":"ZW",
    "gn:dem":1061,
    "gn:feature_class":"P",
    "gn:feature_code":"PPL",
    "gn:name":"Zeka",
    "gn:population":0,
    "gn:timezone":"Africa/Harare",
    "iso:country":"ZW",
    "wof:name":"Zeka",
    "wof:placetype":"locality"
},
  "geometry": {"coordinates":[31.552,-19.62402],"type":"Point"}
}