{
  "type": "Feature",
  "properties": {
    "gn:admin1_code":"1.0",
    "gn:asciiname":"Nheya",
    "gn:country_code":"ZW",
    "gn:dem":964,
    "gn:feature_class":"P",
    "gn:feature_code":"PPL",
    "gn:name":"Nheya",
    "gn:population":0,
    "gn:timezone":"Africa/Harare",
    "iso:country":"ZW",
    "wof:name":"Nheya",
    "wof:placetype":"locality"
},
  "geometry": {"coordinates":[31.79533,-19.39435],"type":"Point"}
}