{
  "type": "Feature",
  "properties": {
    "gn:admin1_code":"08",
    "gn:asciiname":"Gonye",
    "gn:country_code":"ZW",
    "gn:dem":1009,
    "gn:feature_class":"P",
    "gn:feature_code":"PPL",
    "gn:name":"Gonye",
    "gn:population":0,
    "gn:timezone":"Africa/Harare",
    "iso:country":"ZW",
    "wof:name":"Gonye",
    "wof:placetype":"locality"
},
  "geometry": {"coordinates":[31.7758,-19.92596],"type":"Point"}
}