{
  "type": "Feature",
  "properties": {
    "gn:admin1_code":"6.0",
    "gn:asciiname":"Tshinu",
    "gn:country_code":"ZW",
    "gn:dem":1007,
    "gn:feature_class":"P",
    "gn:feature_code":"PPL",
    "gn:name":"Tshinu",
    "gn:population":0,
    "gn:timezone":"Africa/Harare",
    "iso:country":"ZW",
    "name:und_x_variant":[
        "Tshino",
        "Tshinu"
    ],
    "wof:name":"Tshinu",
    "wof:placetype":"locality"
},
  "geometry": {"coordinates":[27.6165,-19.40087],"type":"Point"}
}