{
  "type": "Feature",
  "properties": {
    "gn:admin1_code":"08",
    "gn:asciiname":"Ringisai",
    "gn:country_code":"ZW",
    "gn:dem":1060,
    "gn:feature_class":"P",
    "gn:feature_code":"PPL",
    "gn:name":"Ringisai",
    "gn:population":0,
    "gn:timezone":"Africa/Harare",
    "iso:country":"ZW",
    "wof:name":"Ringisai",
    "wof:placetype":"locality"
},
  "geometry": {"coordinates":[31.5879,-19.64388],"type":"Point"}
}