{
  "type": "Feature",
  "properties": {
    "gn:admin1_code":"1.0",
    "gn:asciiname":"Utete",
    "gn:country_code":"ZW",
    "gn:dem":993,
    "gn:feature_class":"P",
    "gn:feature_code":"PPL",
    "gn:name":"Utete",
    "gn:population":0,
    "gn:timezone":"Africa/Harare",
    "iso:country":"ZW",
    "wof:name":"Utete",
    "wof:placetype":"locality"
},
  "geometry": {"coordinates":[31.79597,-19.44851],"type":"Point"}
}