{
  "type": "Feature",
  "properties": {
    "gn:admin1_code":"1.0",
    "gn:asciiname":"Duvaduve",
    "gn:country_code":"ZW",
    "gn:dem":833,
    "gn:feature_class":"P",
    "gn:feature_code":"PPL",
    "gn:name":"Duvaduve",
    "gn:population":0,
    "gn:timezone":"Africa/Harare",
    "iso:country":"ZW",
    "wof:name":"Duvaduve",
    "wof:placetype":"locality"
},
  "geometry": {"coordinates":[31.90525,-19.28333],"type":"Point"}
}