{
  "type": "Feature",
  "properties": {
    "gn:admin1_code":"08",
    "gn:asciiname":"Mapako",
    "gn:country_code":"ZW",
    "gn:dem":1149,
    "gn:feature_class":"P",
    "gn:feature_code":"PPL",
    "gn:name":"Mapako",
    "gn:population":0,
    "gn:timezone":"Africa/Harare",
    "iso:country":"ZW",
    "wof:name":"Mapako",
    "wof:placetype":"locality"
},
  "geometry": {"coordinates":[31.13317,-19.97726],"type":"Point"}
}