{
  "type": "Feature",
  "properties": {
    "gn:admin1_code":"6.0",
    "gn:asciiname":"Fumabatshena",
    "gn:country_code":"ZW",
    "gn:dem":1021,
    "gn:feature_class":"P",
    "gn:feature_code":"PPL",
    "gn:name":"Fumabatshena",
    "gn:population":0,
    "gn:timezone":"Africa/Harare",
    "iso:country":"ZW",
    "name:und_x_variant":[
        "Fumbatshena",
        "Fumabatshena"
    ],
    "wof:name":"Fumabatshena",
    "wof:placetype":"locality"
},
  "geometry": {"coordinates":[27.55237,-19.20321],"type":"Point"}
}