{
  "type": "Feature",
  "properties": {
    "gn:admin1_code":"6.0",
    "gn:asciiname":"Siyangiya",
    "gn:country_code":"ZW",
    "gn:dem":1194,
    "gn:feature_class":"P",
    "gn:feature_code":"PPL",
    "gn:name":"Siyangiya",
    "gn:population":0,
    "gn:timezone":"Africa/Harare",
    "iso:country":"ZW",
    "wof:name":"Siyangiya",
    "wof:placetype":"locality"
},
  "geometry": {"coordinates":[27.76667,-20.03333],"type":"Point"}
}