{
  "type": "Feature",
  "properties": {
    "gn:admin1_code":"1.0",
    "gn:asciiname":"Shambamuto",
    "gn:country_code":"ZW",
    "gn:dem":977,
    "gn:feature_class":"P",
    "gn:feature_code":"PPL",
    "gn:name":"Shambamuto",
    "gn:population":0,
    "gn:timezone":"Africa/Harare",
    "iso:country":"ZW",
    "wof:name":"Shambamuto",
    "wof:placetype":"locality"
},
  "geometry": {"coordinates":[31.69257,-19.17056],"type":"Point"}
}