{
  "type": "Feature",
  "properties": {
    "gn:admin1_code":"5.0",
    "gn:asciiname":"Dondoro",
    "gn:country_code":"ZW",
    "gn:dem":1151,
    "gn:feature_class":"P",
    "gn:feature_code":"PPL",
    "gn:name":"Dondoro",
    "gn:population":0,
    "gn:timezone":"Africa/Harare",
    "iso:country":"ZW",
    "name:eng_x_preferred":[
        "Dondoro"
    ],
    "wof:name":"Dondoro",
    "wof:placetype":"locality"
},
  "geometry": {"coordinates":[29.8258,-16.57265],"type":"Point"}
}