{
  "type": "Feature",
  "properties": {
    "gn:admin1_code":"8.0",
    "gn:asciiname":"Chief Nhema",
    "gn:country_code":"ZW",
    "gn:dem":752,
    "gn:feature_class":"P",
    "gn:feature_code":"PPL",
    "gn:name":"Chief Nhema",
    "gn:population":0,
    "gn:timezone":"Africa/Harare",
    "iso:country":"ZW",
    "name:eng_x_preferred":[
        "Chief Nhema"
    ],
    "wof:name":"Chief Nhema",
    "wof:placetype":"locality"
},
  "geometry": {"coordinates":[31.58985,-20.25385],"type":"Point"}
}