{
  "type": "Feature",
  "properties": {
    "gn:admin1_code":"5.0",
    "gn:asciiname":"Mapungantsi",
    "gn:country_code":"ZW",
    "gn:dem":1152,
    "gn:feature_class":"P",
    "gn:feature_code":"PPL",
    "gn:name":"Mapungantsi",
    "gn:population":0,
    "gn:timezone":"Africa/Harare",
    "iso:country":"ZW",
    "name:eng_x_preferred":[
        "Mapungantsi"
    ],
    "wof:name":"Mapungantsi",
    "wof:placetype":"locality"
},
  "geometry": {"coordinates":[29.84925,-16.55521],"type":"Point"}
}