{
  "type": "Feature",
  "properties": {
    "gn:admin1_code":"6.0",
    "gn:asciiname":"Kalugus",
    "gn:country_code":"ZW",
    "gn:dem":1040,
    "gn:feature_class":"P",
    "gn:feature_code":"PPL",
    "gn:name":"Kalugus",
    "gn:population":0,
    "gn:timezone":"Africa/Harare",
    "iso:country":"ZW",
    "name:eng_x_preferred":[
        "Kalugus"
    ],
    "name:eng_x_variant":[
        "Kalugus Village"
    ],
    "wof:name":"Kalugus",
    "wof:placetype":"locality"
},
  "geometry": {"coordinates":[27.46486,-18.90116],"type":"Point"}
}