{
  "type": "Feature",
  "properties": {
    "gn:admin1_code":"7.0",
    "gn:asciiname":"Pembe",
    "gn:country_code":"ZW",
    "gn:dem":1062,
    "gn:feature_class":"P",
    "gn:feature_code":"PPL",
    "gn:name":"Pembe",
    "gn:population":0,
    "gn:timezone":"Africa/Harare",
    "iso:country":"ZW",
    "wof:name":"Pembe",
    "wof:placetype":"locality"
},
  "geometry": {"coordinates":[27.26667,-19.93333],"type":"Point"}
}