{
  "type": "Feature",
  "properties": {
    "gn:admin1_code":"3.0",
    "gn:asciiname":"Chief Bepura",
    "gn:country_code":"ZW",
    "gn:dem":1214,
    "gn:feature_class":"P",
    "gn:feature_code":"PPL",
    "gn:name":"Chief Bepura",
    "gn:population":0,
    "gn:timezone":"Africa/Harare",
    "iso:country":"ZW",
    "name:eng_x_preferred":[
        "Chief Bepura"
    ],
    "wof:name":"Chief Bepura",
    "wof:placetype":"locality"
},
  "geometry": {"coordinates":[30.64621,-16.83955],"type":"Point"}
}