{
  "type": "Feature",
  "properties": {
    "gn:admin1_code":"1.0",
    "gn:asciiname":"Tivalire",
    "gn:country_code":"ZW",
    "gn:dem":995,
    "gn:feature_class":"P",
    "gn:feature_code":"PPL",
    "gn:name":"Tivalire",
    "gn:population":0,
    "gn:timezone":"Africa/Harare",
    "iso:country":"ZW",
    "wof:name":"Tivalire",
    "wof:placetype":"locality"
},
  "geometry": {"coordinates":[31.6778,-19.16992],"type":"Point"}
}