{
  "type": "Feature",
  "properties": {
    "gn:admin1_code":"06",
    "gn:asciiname":"Sipepa",
    "gn:country_code":"ZW",
    "gn:dem":999,
    "gn:feature_class":"P",
    "gn:feature_code":"PPL",
    "gn:name":"Sipepa",
    "gn:population":0,
    "gn:timezone":"Africa/Harare",
    "iso:country":"ZW",
    "wof:name":"Sipepa",
    "wof:placetype":"locality"
},
  "geometry": {"coordinates":[27.66044,-19.28113],"type":"Point"}
}