{
  "type": "Feature",
  "properties": {
    "gn:admin1_code":"6.0",
    "gn:asciiname":"Egeekeni",
    "gn:country_code":"ZW",
    "gn:dem":1019,
    "gn:feature_class":"P",
    "gn:feature_code":"PPL",
    "gn:name":"Egeekeni",
    "gn:population":0,
    "gn:timezone":"Africa/Harare",
    "iso:country":"ZW",
    "wof:name":"Egeekeni",
    "wof:placetype":"locality"
},
  "geometry": {"coordinates":[27.64581,-19.24523],"type":"Point"}
}