{
  "type": "Feature",
  "properties": {
    "gn:admin1_code":"2.0",
    "gn:asciiname":"Nenyuka",
    "gn:cc2":"ZW",
    "gn:country_code":"ZW",
    "gn:dem":632,
    "gn:feature_class":"P",
    "gn:feature_code":"PPL",
    "gn:name":"Nenyuka",
    "gn:population":0,
    "gn:timezone":"Africa/Harare",
    "iso:country":"ZW",
    "name:und_x_variant":[
        "Nenyunka",
        "Nenyuka"
    ],
    "wof:name":"Nenyuka",
    "wof:placetype":"locality"
},
  "geometry": {"coordinates":[28.26667,-17.45],"type":"Point"}
}