{
  "type": "Feature",
  "properties": {
    "gn:admin1_code":"7.0",
    "gn:asciiname":"Mabalanas",
    "gn:country_code":"ZW",
    "gn:dem":1069,
    "gn:feature_class":"P",
    "gn:feature_code":"PPL",
    "gn:name":"Mabalanas",
    "gn:population":0,
    "gn:timezone":"Africa/Harare",
    "iso:country":"ZW",
    "wof:name":"Mabalanas",
    "wof:placetype":"locality"
},
  "geometry": {"coordinates":[27.41667,-19.85],"type":"Point"}
}