{
  "type": "Feature",
  "properties": {
    "gn:admin1_code":"08",
    "gn:asciiname":"Chaita",
    "gn:country_code":"ZW",
    "gn:dem":1018,
    "gn:feature_class":"P",
    "gn:feature_code":"PPL",
    "gn:name":"Chaita",
    "gn:population":0,
    "gn:timezone":"Africa/Harare",
    "iso:country":"ZW",
    "wof:name":"Chaita",
    "wof:placetype":"locality"
},
  "geometry": {"coordinates":[31.76246,-19.92008],"type":"Point"}
}