{
  "type": "Feature",
  "properties": {
    "gn:admin1_code":"4.0",
    "gn:asciiname":"Manjonjo",
    "gn:country_code":"ZW",
    "gn:dem":1455,
    "gn:feature_class":"P",
    "gn:feature_code":"PPL",
    "gn:name":"Manjonjo",
    "gn:population":0,
    "gn:timezone":"Africa/Harare",
    "iso:country":"ZW",
    "wof:name":"Manjonjo",
    "wof:placetype":"locality"
},
  "geometry": {"coordinates":[30.96879,-18.88696],"type":"Point"}
}