{
  "type": "Feature",
  "properties": {
    "gn:country":"ZW",
    "gn:fcode":"PPL",
    "gn:population":2148,
    "iso:country":"ZW",
    "name:ara_x_preferred":[
        "\u0628\u0644\u0648\u0645\u062a\u0631\u064a"
    ],
    "name:ceb_x_preferred":[
        "Plumtree"
    ],
    "name:deu_x_preferred":[
        "Plumtree"
    ],
    "name:eng_x_preferred":[
        "Plumtree"
    ],
    "name:fin_x_preferred":[
        "Plumtree"
    ],
    "name:fra_x_preferred":[
        "Plumtree"
    ],
    "name:hrv_x_preferred":[
        "Plumtree"
    ],
    "name:jpn_x_preferred":[
        "\u30d7\u30e9\u30e0\u30c4\u30ea\u30fc"
    ],
    "name:nld_x_preferred":[
        "Plumtree"
    ],
    "name:pol_x_preferred":[
        "Plumtree"
    ],
    "name:por_x_preferred":[
        "Plumtree"
    ],
    "name:spa_x_preferred":[
        "Plumtree"
    ],
    "name:srp_x_preferred":[
        "\u041f\u043b\u0430\u043c\u0442\u0440\u0438"
    ],
    "ne:ADM0CAP":0.0,
    "ne:ADM0NAME":"Zimbabwe",
    "ne:ADM0_A3":"ZWE",
    "ne:ADM1NAME":"Matabeleland South",
    "ne:ADMIN1_COD":0,
    "ne:CAPALT":0,
    "ne:CHANGED":4,
    "ne:CHECKME":0,
    "ne:COMPARE":0,
    "ne:DIFFASCII":0,
    "ne:DIFFNOTE":"Changed scale rank.",
    "ne:ELEVATION":0.0,
    "ne:FEATURECLA":"Populated place",
    "ne:FEATURE_CL":"P",
    "ne:FEATURE_CO":"PPL",
    "ne:GEONAMEID":882859,
    "ne:GEONAMESNO":"Geonames ascii name + lat.d + long.d matching.",
    "ne:GN_ASCII":"Plumtree",
    "ne:GN_POP":2148,
    "ne:GTOPO30":1374.0,
    "ne:ISO_A2":"ZW",
    "ne:LABELRANK":6,
    "ne:LATITUDE":-20.479539,
    "ne:LONGITUDE":27.819997,
    "ne:LS_MATCH":1,
    "ne:LS_NAME":"Plumtree",
    "ne:MAX_AREAKM":2.0,
    "ne:MAX_AREAMI":1.0,
    "ne:MAX_BBXMAX":27.816667,
    "ne:MAX_BBXMIN":27.8,
    "ne:MAX_BBYMAX":-20.483333,
    "ne:MAX_BBYMIN":-20.491667,
    "ne:MAX_NATSCA":10.0,
    "ne:MAX_PERKM":5.0,
    "ne:MAX_PERMI":3.0,
    "ne:MAX_POP10":1771,
    "ne:MAX_POP20":0,
    "ne:MAX_POP300":0,
    "ne:MAX_POP310":0,
    "ne:MAX_POP50":0,
    "ne:MEAN_BBXC":27.808333,
    "ne:MEAN_BBYC":-20.4875,
    "ne:MEGACITY":0,
    "ne:MIN_AREAKM":2.0,
    "ne:MIN_AREAMI":1.0,
    "ne:MIN_BBXMAX":27.816667,
    "ne:MIN_BBXMIN":27.8,
    "ne:MIN_BBYMAX":-20.483333,
    "ne:MIN_BBYMIN":-20.491667,
    "ne:MIN_PERKM":5.0,
    "ne:MIN_PERMI":3.0,
    "ne:NAME":"Plumtree",
    "ne:NAMEASCII":"Plumtree",
    "ne:NAMEDIFF":0,
    "ne:NATSCALE":20,
    "ne:POP1950":0,
    "ne:POP1955":0,
    "ne:POP1960":0,
    "ne:POP1965":0,
    "ne:POP1970":0,
    "ne:POP1975":0,
    "ne:POP1980":0,
    "ne:POP1985":0,
    "ne:POP1990":0,
    "ne:POP1995":0,
    "ne:POP2000":0,
    "ne:POP2005":0,
    "ne:POP2010":0,
    "ne:POP2015":0,
    "ne:POP2020":0,
    "ne:POP2025":0,
    "ne:POP2050":0,
    "ne:POP_MAX":2148,
    "ne:POP_MIN":1771,
    "ne:POP_OTHER":0,
    "ne:RANK_MAX":4,
    "ne:RANK_MIN":3,
    "ne:SCALERANK":7,
    "ne:SOV0NAME":"Zimbabwe",
    "ne:SOV_A3":"ZWE",
    "ne:TIMEZONE":"Africa/Harare",
    "ne:UN_FID":0,
    "ne:UN_LAT":0.0,
    "ne:UN_LONG":0.0,
    "ne:WORLDCITY":0,
    "qs:name":"Plumtree",
    "qs:photos_9r":0,
    "qs:photos_sr":0,
    "qs:pop_sr":"4",
    "wd:wordcount":25,
    "wof:name":"Plumtree",
    "wof:placetype":"locality",
    "wof:population":2148
},
  "geometry": {"coordinates":[27.81667,-20.48333],"type":"Point"}
}