{
  "type": "Feature",
  "properties": {
    "gn:admin1_code":"5.0",
    "gn:asciiname":"Mormon Hill",
    "gn:country_code":"ZW",
    "gn:dem":1143,
    "gn:feature_class":"P",
    "gn:feature_code":"PPL",
    "gn:name":"Mormon Hill",
    "gn:population":0,
    "gn:timezone":"Africa/Harare",
    "iso:country":"ZW",
    "name:eng_x_preferred":[
        "Mormon Hill"
    ],
    "wof:name":"Mormon Hill",
    "wof:placetype":"locality"
},
  "geometry": {"coordinates":[29.88333,-16.73333],"type":"Point"}
}