{
  "type": "Feature",
  "properties": {
    "gn:admin1_code":"6.0",
    "gn:asciiname":"Mandau",
    "gn:country_code":"ZW",
    "gn:dem":1005,
    "gn:feature_class":"P",
    "gn:feature_code":"PPL",
    "gn:name":"Mandau",
    "gn:population":0,
    "gn:timezone":"Africa/Harare",
    "iso:country":"ZW",
    "wof:name":"Mandau",
    "wof:placetype":"locality"
},
  "geometry": {"coordinates":[27.14316,-19.47915],"type":"Point"}
}