{
  "type": "Feature",
  "properties": {
    "gn:admin1_code":"6.0",
    "gn:asciiname":"Dikili",
    "gn:country_code":"ZW",
    "gn:dem":1133,
    "gn:feature_class":"P",
    "gn:feature_code":"PPL",
    "gn:name":"Dikili",
    "gn:population":0,
    "gn:timezone":"Africa/Harare",
    "iso:country":"ZW",
    "name:ceb_x_preferred":[
        "Dikili"
    ],
    "name:deu_x_preferred":[
        "Dikili"
    ],
    "name:diq_x_preferred":[
        "Dikili"
    ],
    "name:ell_x_preferred":[
        "\u0394\u03b5\u03ba\u03b5\u03bb\u03af"
    ],
    "name:epo_x_preferred":[
        "Dikili"
    ],
    "name:fas_x_preferred":[
        "\u062f\u06cc\u06a9\u06cc\u0644\u06cc"
    ],
    "name:fra_x_preferred":[
        "Dikili"
    ],
    "name:mrj_x_preferred":[
        "\u0414\u0438\u043a\u0438\u043b\u0438"
    ],
    "name:msa_x_preferred":[
        "Dikili"
    ],
    "name:nld_x_preferred":[
        "Dikili"
    ],
    "name:nno_x_preferred":[
        "Dikili"
    ],
    "name:nor_x_preferred":[
        "Dikili"
    ],
    "name:rus_x_preferred":[
        "\u0414\u0438\u043a\u0438\u043b\u0438"
    ],
    "name:swa_x_preferred":[
        "Dikili"
    ],
    "name:tur_x_preferred":[
        "Dikili"
    ],
    "name:ukr_x_preferred":[
        "\u0414\u0456\u043a\u0456\u043b\u0456"
    ],
    "name:urd_x_preferred":[
        "\u062f\u06cc\u06a9\u06cc\u0644\u06cc"
    ],
    "name:vie_x_preferred":[
        "Dikili"
    ],
    "name:zho_x_preferred":[
        "\u8fea\u57fa\u5229"
    ],
    "wof:name":"Dikili",
    "wof:placetype":"locality"
},
  "geometry": {"coordinates":[27.75007,-19.86003],"type":"Point"}
}