{
  "type": "Feature",
  "properties": {
    "gn:admin1_code":"6.0",
    "gn:asciiname":"Dikili",
    "gn:country_code":"ZW",
    "gn:dem":1133,
    "gn:feature_class":"P",
    "gn:feature_code":"PPL",
    "gn:name":"Dikili",
    "gn:population":0,
    "gn:timezone":"Africa/Harare",
    "iso:country":"ZW",
    "wof:name":"Dikili",
    "wof:placetype":"locality"
},
  "geometry": {"coordinates":[27.75007,-19.86003],"type":"Point"}
}