{
  "type": "Feature",
  "properties": {
    "gn:admin1_code":"7.0",
    "gn:asciiname":"Kashambi",
    "gn:country_code":"ZW",
    "gn:dem":1121,
    "gn:feature_class":"P",
    "gn:feature_code":"PPL",
    "gn:name":"Kashambi",
    "gn:population":0,
    "gn:timezone":"Africa/Harare",
    "iso:country":"ZW",
    "name:eng_x_preferred":[
        "Kashambi"
    ],
    "wof:name":"Kashambi",
    "wof:placetype":"locality"
},
  "geometry": {"coordinates":[29.87142,-20.02227],"type":"Point"}
}