{
  "type": "Feature",
  "properties": {
    "iso:country":"ZW",
    "name:aze_x_preferred":[
        "Qlendeyl"
    ],
    "name:bar_x_preferred":[
        "Glendale"
    ],
    "name:bel_x_preferred":[
        "\u0413\u043b\u0435\u043d\u0434\u044d\u0439\u043b"
    ],
    "name:bul_x_preferred":[
        "\u0413\u043b\u0435\u043d\u0434\u0435\u0439\u043b"
    ],
    "name:cat_x_preferred":[
        "Glendale"
    ],
    "name:ceb_x_preferred":[
        "Glendale"
    ],
    "name:ces_x_preferred":[
        "Glendale"
    ],
    "name:dan_x_preferred":[
        "Glendale"
    ],
    "name:deu_x_preferred":[
        "Glendale"
    ],
    "name:eng_x_preferred":[
        "Glendale"
    ],
    "name:est_x_preferred":[
        "Glendale"
    ],
    "name:fas_x_preferred":[
        "\u06af\u0644\u0646\u062f\u06cc\u0644"
    ],
    "name:fin_x_preferred":[
        "Glendale"
    ],
    "name:fra_x_preferred":[
        "Glendale"
    ],
    "name:glg_x_preferred":[
        "Glendale"
    ],
    "name:heb_x_preferred":[
        "\u05d2\u05dc\u05e0\u05d3\u05d9\u05d9\u05dc"
    ],
    "name:hrv_x_preferred":[
        "Glendale"
    ],
    "name:hun_x_preferred":[
        "Glendale"
    ],
    "name:ido_x_preferred":[
        "Glendale"
    ],
    "name:ita_x_preferred":[
        "Glendale"
    ],
    "name:jpn_x_preferred":[
        "\u30b0\u30ec\u30f3\u30c7\u30fc\u30eb"
    ],
    "name:kor_x_preferred":[
        "\uae00\ub80c\ub370\uc77c"
    ],
    "name:mlg_x_preferred":[
        "Glendale"
    ],
    "name:nld_x_preferred":[
        "Glendale"
    ],
    "name:nor_x_preferred":[
        "Glendale"
    ],
    "name:pol_x_preferred":[
        "Glendale"
    ],
    "name:por_x_preferred":[
        "Glendale"
    ],
    "name:rus_x_preferred":[
        "\u0413\u043b\u0435\u043d\u0434\u0435\u0439\u043b"
    ],
    "name:slk_x_preferred":[
        "Glendale"
    ],
    "name:spa_x_preferred":[
        "Glendale"
    ],
    "name:srp_x_preferred":[
        "\u0413\u043b\u0435\u043d\u0434\u0435\u0458\u043b"
    ],
    "name:swa_x_preferred":[
        "Glendale"
    ],
    "name:swe_x_preferred":[
        "Glendale"
    ],
    "name:szl_x_preferred":[
        "Glendale"
    ],
    "name:tha_x_preferred":[
        "\u0e40\u0e01\u0e25\u0e47\u0e19\u0e40\u0e14\u0e25"
    ],
    "name:tur_x_preferred":[
        "Glendale"
    ],
    "name:ukr_x_preferred":[
        "\u0413\u043b\u0435\u043d\u0434\u0435\u0439\u043b"
    ],
    "name:urd_x_preferred":[
        "\u06af\u0644\u06cc\u0646\u0688\u06cc\u0644"
    ],
    "name:vol_x_preferred":[
        "Glendale"
    ],
    "qs:gn_country":"ZW",
    "qs:gn_fcode":"PPL",
    "qs:gn_pop":9768,
    "qs:name":"Glendale",
    "qs:name_adm0":"Zimbabwe",
    "qs:name_adm1":"Mashonaland Central",
    "qs:photos":0,
    "qs:photos_1k":0,
    "qs:photos_9k":0,
    "qs:photos_9r":0,
    "qs:photos_all":0,
    "qs:photos_sr":0,
    "qs:placetype":"Town",
    "qs:pop_sr":"5",
    "qs:woe_adm0":23425004,
    "wd:wordcount":247,
    "wof:name":"Glendale",
    "wof:placetype":"locality",
    "wof:population":9768
},
  "geometry": {"coordinates":[31.06718,-17.35514],"type":"Point"}
}