{
  "type": "Feature",
  "properties": {
    "iso:country":"ZW",
    "name:eng_x_preferred":[
        "Glendale"
    ],
    "qs:gn_country":"ZW",
    "qs:gn_fcode":"PPL",
    "qs:gn_pop":9768,
    "qs:name":"Glendale",
    "qs:name_adm0":"Zimbabwe",
    "qs:name_adm1":"Mashonaland Central",
    "qs:photos":0,
    "qs:photos_1k":0,
    "qs:photos_9k":0,
    "qs:photos_9r":0,
    "qs:photos_all":0,
    "qs:photos_sr":0,
    "qs:placetype":"Town",
    "qs:pop_sr":"5",
    "qs:woe_adm0":23425004,
    "wd:wordcount":247,
    "wof:name":"Glendale",
    "wof:placetype":"locality",
    "wof:population":9768
},
  "geometry": {"coordinates":[31.06718,-17.35514],"type":"Point"}
}