{
  "type": "Feature",
  "properties": {
    "gn:admin1_code":"08",
    "gn:asciiname":"Zival",
    "gn:country_code":"ZW",
    "gn:dem":1181,
    "gn:feature_class":"P",
    "gn:feature_code":"PPL",
    "gn:name":"Zival",
    "gn:population":0,
    "gn:timezone":"Africa/Harare",
    "iso:country":"ZW",
    "wof:name":"Zival",
    "wof:placetype":"locality"
},
  "geometry": {"coordinates":[31.65953,-19.98266],"type":"Point"}
}