{
  "type": "Feature",
  "properties": {
    "gn:admin1_code":"6.0",
    "gn:asciiname":"Nqaye",
    "gn:country_code":"ZW",
    "gn:dem":1136,
    "gn:feature_class":"P",
    "gn:feature_code":"PPL",
    "gn:name":"Nqaye",
    "gn:population":0,
    "gn:timezone":"Africa/Harare",
    "iso:country":"ZW",
    "wof:name":"Nqaye",
    "wof:placetype":"locality"
},
  "geometry": {"coordinates":[27.72259,-19.87789],"type":"Point"}
}