{
  "type": "Feature",
  "properties": {
    "gn:admin1_code":"3.0",
    "gn:asciiname":"Nzvimbo",
    "gn:country_code":"ZW",
    "gn:dem":1268,
    "gn:feature_class":"P",
    "gn:feature_code":"PPL",
    "gn:name":"Nzvimbo",
    "gn:population":0,
    "gn:timezone":"Africa/Harare",
    "iso:country":"ZW",
    "name:eng_x_preferred":[
        "Nzvimbo"
    ],
    "wof:name":"Nzvimbo",
    "wof:placetype":"locality"
},
  "geometry": {"coordinates":[31.0475,-17.08041],"type":"Point"}
}