{
  "type": "Feature",
  "properties": {
    "gn:admin1_code":"08",
    "gn:asciiname":"Makuvise",
    "gn:country_code":"ZW",
    "gn:dem":985,
    "gn:feature_class":"P",
    "gn:feature_code":"PPL",
    "gn:name":"Makuvise",
    "gn:population":0,
    "gn:timezone":"Africa/Harare",
    "iso:country":"ZW",
    "wof:name":"Makuvise",
    "wof:placetype":"locality"
},
  "geometry": {"coordinates":[31.7129,-19.62418],"type":"Point"}
}