{
  "type": "Feature",
  "properties": {
    "gn:admin1_code":"7.0",
    "gn:asciiname":"Esibomvu",
    "gn:country_code":"ZW",
    "gn:dem":1168,
    "gn:feature_class":"P",
    "gn:feature_code":"PPL",
    "gn:name":"Esibomvu",
    "gn:population":0,
    "gn:timezone":"Africa/Harare",
    "iso:country":"ZW",
    "name:und_x_variant":[
        "Esimbomvu",
        "Esibomvu"
    ],
    "wof:name":"Esibomvu",
    "wof:placetype":"locality"
},
  "geometry": {"coordinates":[28.8917,-20.39706],"type":"Point"}
}