{
  "type": "Feature",
  "properties": {
    "gn:admin1_code":"8.0",
    "gn:asciiname":"Chief Bota",
    "gn:country_code":"ZW",
    "gn:dem":722,
    "gn:feature_class":"P",
    "gn:feature_code":"PPL",
    "gn:name":"Chief Bota",
    "gn:population":0,
    "gn:timezone":"Africa/Harare",
    "iso:country":"ZW",
    "name:eng_x_preferred":[
        "Chief Bota"
    ],
    "name:eng_x_variant":[
        "Bota"
    ],
    "wof:name":"Chief Bota",
    "wof:placetype":"locality"
},
  "geometry": {"coordinates":[31.40564,-20.56489],"type":"Point"}
}