{
  "type": "Feature",
  "properties": {
    "gn:admin1_code":"5.0",
    "gn:asciiname":"Makuni",
    "gn:country_code":"ZW",
    "gn:dem":1080,
    "gn:feature_class":"P",
    "gn:feature_code":"PPL",
    "gn:name":"Makuni",
    "gn:population":0,
    "gn:timezone":"Africa/Harare",
    "iso:country":"ZW",
    "name:eng_x_preferred":[
        "Makuni"
    ],
    "wof:name":"Makuni",
    "wof:placetype":"locality"
},
  "geometry": {"coordinates":[29.9355,-16.60068],"type":"Point"}
}