{
  "type": "Feature",
  "properties": {
    "gn:admin1_code":"08",
    "gn:asciiname":"Musundire",
    "gn:country_code":"ZW",
    "gn:dem":862,
    "gn:feature_class":"P",
    "gn:feature_code":"PPL",
    "gn:name":"Musundire",
    "gn:population":0,
    "gn:timezone":"Africa/Harare",
    "iso:country":"ZW",
    "wof:name":"Musundire",
    "wof:placetype":"locality"
},
  "geometry": {"coordinates":[31.75785,-19.79905],"type":"Point"}
}