{
  "type": "Feature",
  "properties": {
    "gn:admin1_code":"08",
    "gn:asciiname":"Mhuru",
    "gn:country_code":"ZW",
    "gn:dem":853,
    "gn:feature_class":"P",
    "gn:feature_code":"PPL",
    "gn:name":"Mhuru",
    "gn:population":0,
    "gn:timezone":"Africa/Harare",
    "iso:country":"ZW",
    "wof:name":"Mhuru",
    "wof:placetype":"locality"
},
  "geometry": {"coordinates":[31.80534,-19.83527],"type":"Point"}
}