{
  "type": "Feature",
  "properties": {
    "gn:admin1_code":"8.0",
    "gn:asciiname":"Hippo Valley",
    "gn:country_code":"ZW",
    "gn:dem":351,
    "gn:feature_class":"P",
    "gn:feature_code":"PPL",
    "gn:name":"Hippo Valley",
    "gn:population":0,
    "gn:timezone":"Africa/Harare",
    "iso:country":"ZW",
    "wof:name":"Hippo Valley",
    "wof:placetype":"locality"
},
  "geometry": {"coordinates":[31.55,-21.16667],"type":"Point"}
}