{
  "type": "Feature",
  "properties": {
    "gn:admin1_code":"8.0",
    "gn:asciiname":"Musungo",
    "gn:country_code":"ZW",
    "gn:dem":925,
    "gn:feature_class":"P",
    "gn:feature_code":"PPL",
    "gn:name":"Musungo",
    "gn:population":0,
    "gn:timezone":"Africa/Harare",
    "iso:country":"ZW",
    "wof:name":"Musungo",
    "wof:placetype":"locality"
},
  "geometry": {"coordinates":[31.78374,-19.61243],"type":"Point"}
}