{
  "type": "Feature",
  "properties": {
    "gn:admin1_code":"10.0",
    "gn:asciiname":"Zengeza",
    "gn:country_code":"ZW",
    "gn:dem":1432,
    "gn:feature_class":"P",
    "gn:feature_code":"PPLL",
    "gn:name":"Zengeza",
    "gn:population":0,
    "gn:timezone":"Africa/Harare",
    "iso:country":"ZW",
    "wof:name":"Zengeza",
    "wof:placetype":"locality"
},
  "geometry": {"coordinates":[31.06518,-18.01343],"type":"Point"}
}