{
  "type": "Feature",
  "properties": {
    "gn:admin1_code":"4.0",
    "gn:asciiname":"Muchato",
    "gn:country_code":"ZW",
    "gn:dem":1214,
    "gn:feature_class":"P",
    "gn:feature_code":"PPL",
    "gn:name":"Muchato",
    "gn:population":0,
    "gn:timezone":"Africa/Harare",
    "iso:country":"ZW",
    "wof:name":"Muchato",
    "wof:placetype":"locality"
},
  "geometry": {"coordinates":[31.51915,-17.77604],"type":"Point"}
}