{
  "type": "Feature",
  "properties": {
    "gn:admin1_code":"8.0",
    "gn:asciiname":"Mapfumo",
    "gn:country_code":"ZW",
    "gn:dem":962,
    "gn:feature_class":"P",
    "gn:feature_code":"PPL",
    "gn:name":"Mapfumo",
    "gn:population":0,
    "gn:timezone":"Africa/Harare",
    "iso:country":"ZW",
    "wof:name":"Mapfumo",
    "wof:placetype":"locality"
},
  "geometry": {"coordinates":[31.6697,-19.50839],"type":"Point"}
}