{
  "type": "Feature",
  "properties": {
    "gn:admin1_code":"10.0",
    "gn:asciiname":"Dungarven",
    "gn:country_code":"ZW",
    "gn:dem":1527,
    "gn:feature_class":"P",
    "gn:feature_code":"PPL",
    "gn:name":"Dungarven",
    "gn:population":0,
    "gn:timezone":"Africa/Harare",
    "iso:country":"ZW",
    "name:eng_x_preferred":[
        "Dungarven"
    ],
    "wof:name":"Dungarven",
    "wof:placetype":"locality"
},
  "geometry": {"coordinates":[31.09306,-17.75639],"type":"Point"}
}