{
  "type": "Feature",
  "properties": {
    "gn:admin1_code":"4.0",
    "gn:asciiname":"Arcturus",
    "gn:country_code":"ZW",
    "gn:dem":1357,
    "gn:feature_class":"P",
    "gn:feature_code":"PPL",
    "gn:name":"Arcturus",
    "gn:population":0,
    "gn:timezone":"Africa/Harare",
    "iso:country":"ZW",
    "name:bar_x_preferred":[
        "Arcturas"
    ],
    "name:eng_x_preferred":[
        "Arcturus"
    ],
    "name:eng_x_variant":[
        "Arcturas"
    ],
    "wof:name":"Arcturus",
    "wof:placetype":"locality"
},
  "geometry": {"coordinates":[31.33127,-17.78271],"type":"Point"}
}