{
  "type": "Feature",
  "properties": {
    "gn:admin1_code":"8.0",
    "gn:asciiname":"Fuve",
    "gn:country_code":"ZW",
    "gn:dem":1049,
    "gn:feature_class":"P",
    "gn:feature_code":"PPL",
    "gn:name":"Fuve",
    "gn:population":0,
    "gn:timezone":"Africa/Harare",
    "iso:country":"ZW",
    "wof:name":"Fuve",
    "wof:placetype":"locality"
},
  "geometry": {"coordinates":[31.5177,-19.3953],"type":"Point"}
}