{
  "type": "Feature",
  "properties": {
    "gn:admin1_code":"06",
    "gn:asciiname":"Lagisa",
    "gn:country_code":"ZW",
    "gn:dem":1001,
    "gn:feature_class":"P",
    "gn:feature_code":"PPL",
    "gn:name":"Lagisa",
    "gn:population":0,
    "gn:timezone":"Africa/Harare",
    "iso:country":"ZW",
    "wof:name":"Lagisa",
    "wof:placetype":"locality"
},
  "geometry": {"coordinates":[27.01602,-19.81046],"type":"Point"}
}