{
  "type": "Feature",
  "properties": {
    "gn:admin1_code":"6.0",
    "gn:asciiname":"Pumula",
    "gn:country_code":"ZW",
    "gn:dem":1023,
    "gn:feature_class":"P",
    "gn:feature_code":"PPL",
    "gn:name":"Pumula",
    "gn:population":0,
    "gn:timezone":"Africa/Harare",
    "iso:country":"ZW",
    "wof:name":"Pumula",
    "wof:placetype":"locality"
},
  "geometry": {"coordinates":[27.53613,-19.33606],"type":"Point"}
}