{
  "type": "Feature",
  "properties": {
    "gn:admin1_code":"06",
    "gn:asciiname":"Siganda",
    "gn:country_code":"ZW",
    "gn:dem":1161,
    "gn:feature_class":"P",
    "gn:feature_code":"PPL",
    "gn:name":"Siganda",
    "gn:population":0,
    "gn:timezone":"Africa/Harare",
    "iso:country":"ZW",
    "wof:name":"Siganda",
    "wof:placetype":"locality"
},
  "geometry": {"coordinates":[28.47618,-19.33297],"type":"Point"}
}