{
  "type": "Feature",
  "properties": {
    "gn:admin1_code":"1.0",
    "gn:asciiname":"Cashel",
    "gn:country_code":"ZW",
    "gn:dem":1231,
    "gn:feature_class":"P",
    "gn:feature_code":"PPL",
    "gn:name":"Cashel",
    "gn:population":0,
    "gn:timezone":"Africa/Harare",
    "iso:country":"ZW",
    "name:por_x_preferred":[
        "Cashel"
    ],
    "name:sna_x_preferred":[
        "Cashel"
    ],
    "wof:name":"Cashel",
    "wof:placetype":"locality"
},
  "geometry": {"coordinates":[32.78333,-19.55],"type":"Point"}
}