{
  "type": "Feature",
  "properties": {
    "gn:admin1_code":"3.0",
    "gn:asciiname":"Chiweshe",
    "gn:country_code":"ZW",
    "gn:dem":1245,
    "gn:feature_class":"P",
    "gn:feature_code":"PPL",
    "gn:name":"Chiweshe",
    "gn:population":0,
    "gn:timezone":"Africa/Harare",
    "iso:country":"ZW",
    "name:eng_x_preferred":[
        "Chiweshe"
    ],
    "wof:name":"Chiweshe",
    "wof:placetype":"locality"
},
  "geometry": {"coordinates":[31.12249000000001,-16.88337000000001],"type":"Point"}
}