{
  "type": "Feature",
  "properties": {
    "gn:admin1_code":"08",
    "gn:asciiname":"Mondo",
    "gn:country_code":"ZW",
    "gn:dem":912,
    "gn:feature_class":"P",
    "gn:feature_code":"PPL",
    "gn:name":"Mondo",
    "gn:population":0,
    "gn:timezone":"Africa/Harare",
    "iso:country":"ZW",
    "name:ceb_x_preferred":[
        "Mondo"
    ],
    "name:deu_x_preferred":[
        "Mondo"
    ],
    "name:fin_x_preferred":[
        "Mondo"
    ],
    "name:fra_x_preferred":[
        "Mondo"
    ],
    "name:ita_x_preferred":[
        "Mondo"
    ],
    "name:rus_x_preferred":[
        "\u041c\u043e\u043d\u0434\u043e"
    ],
    "name:spa_x_preferred":[
        "Mondo"
    ],
    "name:swa_x_preferred":[
        "Mondo"
    ],
    "name:swe_x_preferred":[
        "Mondo"
    ],
    "wof:name":"Mondo",
    "wof:placetype":"locality"
},
  "geometry": {"coordinates":[31.79073,-19.98012],"type":"Point"}
}