{
  "type": "Feature",
  "properties": {
    "gn:admin1_code":"8.0",
    "gn:asciiname":"Mudadi",
    "gn:country_code":"ZW",
    "gn:dem":1051,
    "gn:feature_class":"P",
    "gn:feature_code":"PPL",
    "gn:name":"Mudadi",
    "gn:population":0,
    "gn:timezone":"Africa/Harare",
    "iso:country":"ZW",
    "wof:name":"Mudadi",
    "wof:placetype":"locality"
},
  "geometry": {"coordinates":[31.54327,-19.43072],"type":"Point"}
}