{
  "type": "Feature",
  "properties": {
    "gn:admin1_code":"08",
    "gn:asciiname":"Kwangare",
    "gn:country_code":"ZW",
    "gn:dem":987,
    "gn:feature_class":"P",
    "gn:feature_code":"PPL",
    "gn:name":"Kwangare",
    "gn:population":0,
    "gn:timezone":"Africa/Harare",
    "iso:country":"ZW",
    "wof:name":"Kwangare",
    "wof:placetype":"locality"
},
  "geometry": {"coordinates":[31.67669,-19.64705],"type":"Point"}
}