{
  "type": "Feature",
  "properties": {
    "gn:admin1_code":"6.0",
    "gn:asciiname":"Sitambala",
    "gn:country_code":"ZW",
    "gn:dem":1021,
    "gn:feature_class":"P",
    "gn:feature_code":"PPL",
    "gn:name":"Sitambala",
    "gn:population":0,
    "gn:timezone":"Africa/Harare",
    "iso:country":"ZW",
    "name:und_x_variant":[
        "Sitambarara",
        "Sitambala"
    ],
    "wof:name":"Sitambala",
    "wof:placetype":"locality"
},
  "geometry": {"coordinates":[27.50978,-19.16322000000001],"type":"Point"}
}