{
  "type": "Feature",
  "properties": {
    "gn:admin1_code":"08",
    "gn:asciiname":"Muruzi",
    "gn:country_code":"ZW",
    "gn:dem":891,
    "gn:feature_class":"P",
    "gn:feature_code":"PPL",
    "gn:name":"Muruzi",
    "gn:population":0,
    "gn:timezone":"Africa/Harare",
    "iso:country":"ZW",
    "wof:name":"Muruzi",
    "wof:placetype":"locality"
},
  "geometry": {"coordinates":[31.89286,-19.8683],"type":"Point"}
}