{
  "type": "Feature",
  "properties": {
    "gn:admin1_code":"6.0",
    "gn:asciiname":"Mashula",
    "gn:country_code":"ZW",
    "gn:dem":1011,
    "gn:feature_class":"P",
    "gn:feature_code":"PPL",
    "gn:name":"Mashula",
    "gn:population":0,
    "gn:timezone":"Africa/Harare",
    "iso:country":"ZW",
    "name:und_x_variant":[
        "Mashule",
        "Mashula"
    ],
    "wof:name":"Mashula",
    "wof:placetype":"locality"
},
  "geometry": {"coordinates":[27.38769000000001,-19.34142],"type":"Point"}
}