{
  "type": "Feature",
  "properties": {
    "gn:admin1_code":"1.0",
    "gn:asciiname":"Chizema",
    "gn:country_code":"ZW",
    "gn:dem":939,
    "gn:feature_class":"P",
    "gn:feature_code":"PPL",
    "gn:name":"Chizema",
    "gn:population":0,
    "gn:timezone":"Africa/Harare",
    "iso:country":"ZW",
    "wof:name":"Chizema",
    "wof:placetype":"locality"
},
  "geometry": {"coordinates":[31.91351,-19.46297],"type":"Point"}
}