{
  "type": "Feature",
  "properties": {
    "gn:admin1_code":"08",
    "gn:asciiname":"Nhambu",
    "gn:country_code":"ZW",
    "gn:dem":968,
    "gn:feature_class":"P",
    "gn:feature_code":"PPL",
    "gn:name":"Nhambu",
    "gn:population":0,
    "gn:timezone":"Africa/Harare",
    "iso:country":"ZW",
    "wof:name":"Nhambu",
    "wof:placetype":"locality"
},
  "geometry": {"coordinates":[31.63587,-19.8853],"type":"Point"}
}