{
  "type": "Feature",
  "properties": {
    "gn:admin1_code":"6.0",
    "gn:asciiname":"Nyakatha",
    "gn:country_code":"ZW",
    "gn:dem":1131,
    "gn:feature_class":"P",
    "gn:feature_code":"PPL",
    "gn:name":"Nyakatha",
    "gn:population":0,
    "gn:timezone":"Africa/Harare",
    "iso:country":"ZW",
    "wof:name":"Nyakatha",
    "wof:placetype":"locality"
},
  "geometry": {"coordinates":[27.78333,-19.85],"type":"Point"}
}