{
  "type": "Feature",
  "properties": {
    "gn:admin1_code":"6.0",
    "gn:asciiname":"Dandamjena",
    "gn:country_code":"ZW",
    "gn:dem":1017,
    "gn:feature_class":"P",
    "gn:feature_code":"PPL",
    "gn:name":"Dandamjena",
    "gn:population":0,
    "gn:timezone":"Africa/Harare",
    "iso:country":"ZW",
    "wof:name":"Dandamjena",
    "wof:placetype":"locality"
},
  "geometry": {"coordinates":[27.35906,-19.53578],"type":"Point"}
}