{
  "type": "Feature",
  "properties": {
    "gn:admin1_code":"04",
    "gn:asciiname":"Shangure",
    "gn:country_code":"ZW",
    "gn:dem":1383,
    "gn:feature_class":"P",
    "gn:feature_code":"PPL",
    "gn:name":"Shangure",
    "gn:population":0,
    "gn:timezone":"Africa/Harare",
    "iso:country":"ZW",
    "name:eng_x_preferred":[
        "Shangure"
    ],
    "wof:name":"Shangure",
    "wof:placetype":"locality"
},
  "geometry": {"coordinates":[31.54766,-17.93855],"type":"Point"}
}