{
  "type": "Feature",
  "properties": {
    "gn:admin1_code":"6.0",
    "gn:asciiname":"Mtawalos",
    "gn:country_code":"ZW",
    "gn:dem":1031,
    "gn:feature_class":"P",
    "gn:feature_code":"PPL",
    "gn:name":"Mtawalos",
    "gn:population":0,
    "gn:timezone":"Africa/Harare",
    "iso:country":"ZW",
    "name:eng_x_preferred":[
        "Mtawalos"
    ],
    "name:eng_x_variant":[
        "Mtawalos Village"
    ],
    "wof:name":"Mtawalos",
    "wof:placetype":"locality"
},
  "geometry": {"coordinates":[27.52288,-18.9486],"type":"Point"}
}