{
  "type": "Feature",
  "properties": {
    "gn:admin1_code":"5.0",
    "gn:asciiname":"Hondo",
    "gn:country_code":"ZW",
    "gn:dem":1216,
    "gn:feature_class":"P",
    "gn:feature_code":"PPL",
    "gn:name":"Hondo",
    "gn:population":0,
    "gn:timezone":"Africa/Harare",
    "iso:country":"ZW",
    "name:ceb_x_preferred":[
        "Hondo"
    ],
    "name:deu_x_preferred":[
        "Hondo"
    ],
    "name:eng_x_preferred":[
        "Hondo"
    ],
    "name:fra_x_preferred":[
        "Hondo"
    ],
    "name:ita_x_preferred":[
        "Hondo"
    ],
    "name:nds_x_preferred":[
        "Hondo"
    ],
    "name:nld_x_preferred":[
        "Hondo"
    ],
    "name:por_x_preferred":[
        "Hondo"
    ],
    "name:spa_x_preferred":[
        "Hondo"
    ],
    "name:swe_x_preferred":[
        "Hondo"
    ],
    "wof:name":"Hondo",
    "wof:placetype":"locality"
},
  "geometry": {"coordinates":[29.43041,-16.78051],"type":"Point"}
}