{
  "type": "Feature",
  "properties": {
    "gn:admin1_code":"8.0",
    "gn:asciiname":"Tavura",
    "gn:country_code":"ZW",
    "gn:dem":988,
    "gn:feature_class":"P",
    "gn:feature_code":"PPL",
    "gn:name":"Tavura",
    "gn:population":0,
    "gn:timezone":"Africa/Harare",
    "iso:country":"ZW",
    "wof:name":"Tavura",
    "wof:placetype":"locality"
},
  "geometry": {"coordinates":[31.64047,-19.52412],"type":"Point"}
}