{
  "type": "Feature",
  "properties": {
    "iso:country":"ZW",
    "name:eng_x_preferred":[
        "Belvedere North"
    ],
    "name:eng_x_variant":[
        "Belvedere"
    ],
    "name:unk_x_variant":[
        "Belvedere"
    ],
    "qs:gn_country":"ZW",
    "qs:gn_fcode":"PPLX",
    "qs:gn_pop":0,
    "qs:name":"Belvedere North",
    "qs:name_adm0":"Zimbabwe",
    "qs:name_adm1":"Harare",
    "qs:photos":1,
    "qs:photos_1k":1,
    "qs:photos_9k":1,
    "qs:photos_9r":1,
    "qs:photos_all":1,
    "qs:photos_sr":1,
    "qs:placetype":"Suburb",
    "qs:pop_sr":"0",
    "qs:woe_adm0":23425004,
    "wof:name":"Belvedere North",
    "wof:placetype":"neighbourhood"
},
  "geometry": {"coordinates":[31.01806,-17.82111],"type":"Point"}
}