{
  "type": "Feature",
  "properties": {
    "gn:admin1_code":"6.0",
    "gn:asciiname":"Spingwini",
    "gn:country_code":"ZW",
    "gn:dem":1119,
    "gn:feature_class":"P",
    "gn:feature_code":"PPL",
    "gn:name":"Spingwini",
    "gn:population":0,
    "gn:timezone":"Africa/Harare",
    "iso:country":"ZW",
    "wof:name":"Spingwini",
    "wof:placetype":"locality"
},
  "geometry": {"coordinates":[27.7928,-19.82441],"type":"Point"}
}