{
  "type": "Feature",
  "properties": {
    "gn:admin1_code":"6.0",
    "gn:asciiname":"Mbowani",
    "gn:country_code":"ZW",
    "gn:dem":1111,
    "gn:feature_class":"P",
    "gn:feature_code":"PPL",
    "gn:name":"Mbowani",
    "gn:population":0,
    "gn:timezone":"Africa/Harare",
    "iso:country":"ZW",
    "wof:name":"Mbowani",
    "wof:placetype":"locality"
},
  "geometry": {"coordinates":[27.83321,-19.87526],"type":"Point"}
}