{
  "type": "Feature",
  "properties": {
    "gn:admin1_code":"6.0",
    "gn:asciiname":"Tshiyakwaklwe",
    "gn:country_code":"ZW",
    "gn:dem":1024,
    "gn:feature_class":"P",
    "gn:feature_code":"PPL",
    "gn:name":"Tshiyakwaklwe",
    "gn:population":0,
    "gn:timezone":"Africa/Harare",
    "iso:country":"ZW",
    "wof:name":"Tshiyakwaklwe",
    "wof:placetype":"locality"
},
  "geometry": {"coordinates":[27.52168,-19.42089],"type":"Point"}
}