{
  "type": "Feature",
  "properties": {
    "gn:admin1_code":"04",
    "gn:asciiname":"Westgate",
    "gn:country_code":"ZW",
    "gn:dem":1532,
    "gn:feature_class":"P",
    "gn:feature_code":"PPL",
    "gn:name":"Westgate",
    "gn:population":0,
    "gn:timezone":"Africa/Harare",
    "iso:country":"ZW",
    "name:deu_x_preferred":[
        "Westgate"
    ],
    "name:fra_x_preferred":[
        "Westgate"
    ],
    "name:ita_x_preferred":[
        "Westgate"
    ],
    "name:kor_x_preferred":[
        "\uc6e8\uc2a4\ud2b8\uac8c\uc774\ud2b8"
    ],
    "name:nld_x_preferred":[
        "Westgate"
    ],
    "name:pol_x_preferred":[
        "Westgate"
    ],
    "name:por_x_preferred":[
        "Westgate"
    ],
    "name:srp_x_preferred":[
        "\u0412\u0435\u0441\u0442\u0433\u0435\u0458\u0442"
    ],
    "name:swe_x_preferred":[
        "Westgate"
    ],
    "wof:name":"Westgate",
    "wof:placetype":"locality"
},
  "geometry": {"coordinates":[31.09732,-17.76637999999999],"type":"Point"}
}