{
  "type": "Feature",
  "properties": {
    "gn:admin1_code":"04",
    "gn:asciiname":"Westgate",
    "gn:country_code":"ZW",
    "gn:dem":1532,
    "gn:feature_class":"P",
    "gn:feature_code":"PPL",
    "gn:name":"Westgate",
    "gn:population":0,
    "gn:timezone":"Africa/Harare",
    "iso:country":"ZW",
    "wof:name":"Westgate",
    "wof:placetype":"locality"
},
  "geometry": {"coordinates":[31.09732,-17.76637999999999],"type":"Point"}
}