{
  "type": "Feature",
  "properties": {
    "gn:admin1_code":"4.0",
    "gn:asciiname":"Mahusekwa",
    "gn:country_code":"ZW",
    "gn:dem":1486,
    "gn:feature_class":"P",
    "gn:feature_code":"PPL",
    "gn:name":"Mahusekwa",
    "gn:population":0,
    "gn:timezone":"Africa/Harare",
    "iso:country":"ZW",
    "wof:name":"Mahusekwa",
    "wof:placetype":"locality"
},
  "geometry": {"coordinates":[31.19832,-18.30404],"type":"Point"}
}