{
  "type": "Feature",
  "properties": {
    "gn:admin1_code":"01",
    "gn:asciiname":"Chibuwe",
    "gn:country_code":"ZW",
    "gn:dem":431,
    "gn:feature_class":"P",
    "gn:feature_code":"PPL",
    "gn:name":"Chibuwe",
    "gn:population":0,
    "gn:timezone":"Africa/Harare",
    "iso:country":"ZW",
    "name:eng_x_preferred":[
        "Chibuwe"
    ],
    "wof:name":"Chibuwe",
    "wof:placetype":"locality"
},
  "geometry": {"coordinates":[32.31287,-20.45663],"type":"Point"}
}