{
  "type": "Feature",
  "properties": {
    "iso:country":"ZW",
    "name:bar_x_preferred":[
        "Newlands"
    ],
    "name:ceb_x_preferred":[
        "Newlands"
    ],
    "name:deu_x_preferred":[
        "Newlands"
    ],
    "name:eng_x_preferred":[
        "Newlands"
    ],
    "name:fra_x_preferred":[
        "Newlands"
    ],
    "name:pol_x_preferred":[
        "Newlands"
    ],
    "name:rus_x_preferred":[
        "\u041d\u044c\u044e\u043b\u0435\u043d\u0434\u0441"
    ],
    "name:ukr_x_preferred":[
        "\u041d\u044c\u044e\u043b\u0435\u043d\u0434\u0441"
    ],
    "qs:gn_country":"ZW",
    "qs:gn_fcode":"PPLX",
    "qs:gn_pop":0,
    "qs:name":"Newlands",
    "qs:name_adm0":"Zimbabwe",
    "qs:name_adm1":"Harare",
    "qs:photos":2,
    "qs:photos_1k":1,
    "qs:photos_9k":1,
    "qs:photos_9r":1,
    "qs:photos_all":2,
    "qs:photos_sr":1,
    "qs:placetype":"Suburb",
    "qs:pop_sr":"0",
    "qs:woe_adm0":23425004,
    "wd:wordcount":134,
    "wof:name":"Newlands",
    "wof:placetype":"neighbourhood"
},
  "geometry": {"coordinates":[31.08167,-17.80806],"type":"Point"}
}