{
  "type": "Feature",
  "properties": {
    "gn:admin1_code":"5.0",
    "gn:asciiname":"Umsweswe",
    "gn:cc2":"ZW",
    "gn:country_code":"ZW",
    "gn:dem":1082,
    "gn:feature_class":"P",
    "gn:feature_code":"PPL",
    "gn:name":"Umsweswe",
    "gn:population":0,
    "gn:timezone":"Africa/Harare",
    "iso:country":"ZW",
    "name:und_x_variant":[
        "Sweswe",
        "Umsweswe Siding",
        "Umsweswe"
    ],
    "wof:name":"Umsweswe",
    "wof:placetype":"locality"
},
  "geometry": {"coordinates":[29.81667,-18.45],"type":"Point"}
}