{
  "type": "Feature",
  "properties": {
    "gn:admin1_code":"04",
    "gn:asciiname":"Chinyika",
    "gn:country_code":"ZW",
    "gn:dem":1380,
    "gn:feature_class":"P",
    "gn:feature_code":"PPL",
    "gn:name":"Chinyika",
    "gn:population":0,
    "gn:timezone":"Africa/Harare",
    "iso:country":"ZW",
    "name:eng_x_preferred":[
        "Chinyika"
    ],
    "wof:name":"Chinyika",
    "wof:placetype":"locality"
},
  "geometry": {"coordinates":[31.33848,-17.8262],"type":"Point"}
}