{
  "type": "Feature",
  "properties": {
    "gn:admin1_code":"08",
    "gn:asciiname":"Toringepi",
    "gn:country_code":"ZW",
    "gn:dem":992,
    "gn:feature_class":"P",
    "gn:feature_code":"PPL",
    "gn:name":"Toringepi",
    "gn:population":0,
    "gn:timezone":"Africa/Harare",
    "iso:country":"ZW",
    "wof:name":"Toringepi",
    "wof:placetype":"locality"
},
  "geometry": {"coordinates":[31.84552,-19.82034],"type":"Point"}
}