{
  "type": "Feature",
  "properties": {
    "gn:admin1_code":"2.0",
    "gn:asciiname":"Mbungu Settlement",
    "gn:country_code":"ZW",
    "gn:dem":1074,
    "gn:feature_class":"P",
    "gn:feature_code":"PPL",
    "gn:name":"Mbungu Settlement",
    "gn:population":0,
    "gn:timezone":"Africa/Harare",
    "iso:country":"ZW",
    "name:eng_x_preferred":[
        "Mbungu Settlement"
    ],
    "wof:name":"Mbungu Settlement",
    "wof:placetype":"locality"
},
  "geometry": {"coordinates":[28.02617,-18.40713],"type":"Point"}
}