{
  "type": "Feature",
  "properties": {
    "gn:admin1_code":"5.0",
    "gn:asciiname":"Neuso Business Centre",
    "gn:country_code":"ZW",
    "gn:dem":1256,
    "gn:feature_class":"P",
    "gn:feature_code":"PPL",
    "gn:name":"Neuso Business Centre",
    "gn:population":0,
    "gn:timezone":"Africa/Harare",
    "iso:country":"ZW",
    "wof:name":"Neuso Business Centre",
    "wof:placetype":"locality"
},
  "geometry": {"coordinates":[30.53333,-18.53333],"type":"Point"}
}