{
  "type": "Feature",
  "properties": {
    "gn:admin1_code":"9.0",
    "gn:asciiname":"Pumula",
    "gn:country_code":"ZW",
    "gn:dem":1359,
    "gn:feature_class":"P",
    "gn:feature_code":"PPL",
    "gn:name":"Pumula",
    "gn:population":0,
    "gn:timezone":"Africa/Harare",
    "iso:country":"ZW",
    "name:und_x_variant":[
        "Pamula",
        "Pumula African Township",
        "Pumula"
    ],
    "wof:name":"Pumula",
    "wof:placetype":"locality"
},
  "geometry": {"coordinates":[28.47333,-20.14444],"type":"Point"}
}