{
  "type": "Feature",
  "properties": {
    "gn:admin1_code":"1.0",
    "gn:asciiname":"Dzapasi",
    "gn:country_code":"ZW",
    "gn:dem":1021,
    "gn:feature_class":"P",
    "gn:feature_code":"PPL",
    "gn:name":"Dzapasi",
    "gn:population":0,
    "gn:timezone":"Africa/Harare",
    "iso:country":"ZW",
    "wof:name":"Dzapasi",
    "wof:placetype":"locality"
},
  "geometry": {"coordinates":[31.86109,-19.43263],"type":"Point"}
}