{
  "type": "Feature",
  "properties": {
    "gn:admin1_code":"5.0",
    "gn:asciiname":"Mpagari",
    "gn:country_code":"ZW",
    "gn:dem":1212,
    "gn:feature_class":"P",
    "gn:feature_code":"PPL",
    "gn:name":"Mpagari",
    "gn:population":0,
    "gn:timezone":"Africa/Harare",
    "iso:country":"ZW",
    "name:eng_x_preferred":[
        "Mpagari"
    ],
    "wof:name":"Mpagari",
    "wof:placetype":"locality"
},
  "geometry": {"coordinates":[29.67038,-16.46271],"type":"Point"}
}