{
  "type": "Feature",
  "properties": {
    "gn:admin1_code":"08",
    "gn:asciiname":"Mashako",
    "gn:country_code":"ZW",
    "gn:dem":947,
    "gn:feature_class":"P",
    "gn:feature_code":"PPL",
    "gn:name":"Mashako",
    "gn:population":0,
    "gn:timezone":"Africa/Harare",
    "iso:country":"ZW",
    "wof:name":"Mashako",
    "wof:placetype":"locality"
},
  "geometry": {"coordinates":[31.6643,-19.83828],"type":"Point"}
}