{
  "type": "Feature",
  "properties": {
    "gn:admin1_code":"6.0",
    "gn:asciiname":"Ensedhlwini",
    "gn:country_code":"ZW",
    "gn:dem":1059,
    "gn:feature_class":"P",
    "gn:feature_code":"PPL",
    "gn:name":"Ensedhlwini",
    "gn:population":0,
    "gn:timezone":"Africa/Harare",
    "iso:country":"ZW",
    "name:und_x_variant":[
        "Sedhlwini",
        "Ensedhlwini"
    ],
    "wof:name":"Ensedhlwini",
    "wof:placetype":"locality"
},
  "geometry": {"coordinates":[27.47668,-19.70221],"type":"Point"}
}