{
  "type": "Feature",
  "properties": {
    "gn:admin1_code":"08",
    "gn:asciiname":"Mupuwi",
    "gn:country_code":"ZW",
    "gn:dem":885,
    "gn:feature_class":"P",
    "gn:feature_code":"PPL",
    "gn:name":"Mupuwi",
    "gn:population":0,
    "gn:timezone":"Africa/Harare",
    "iso:country":"ZW",
    "wof:name":"Mupuwi",
    "wof:placetype":"locality"
},
  "geometry": {"coordinates":[31.68161,-19.81208],"type":"Point"}
}