{
  "type": "Feature",
  "properties": {
    "gn:admin1_code":"4.0",
    "gn:asciiname":"Makosa Township",
    "gn:country_code":"ZW",
    "gn:dem":967,
    "gn:feature_class":"P",
    "gn:feature_code":"PPL",
    "gn:name":"Makosa Township",
    "gn:population":0,
    "gn:timezone":"Africa/Harare",
    "iso:country":"ZW",
    "name:und_x_variant":[
        "Makosa Business Centre",
        "Makosa Township"
    ],
    "wof:name":"Makosa Township",
    "wof:placetype":"locality"
},
  "geometry": {"coordinates":[32.47352,-17.27239],"type":"Point"}
}