{
  "type": "Feature",
  "properties": {
    "gn:country":"ZW",
    "gn:fcode":"PPL",
    "gn:population":3835,
    "iso:country":"ZW",
    "name:eng_x_preferred":[
        "Shangani"
    ],
    "name:nld_x_preferred":[
        "Shangani"
    ],
    "qs:name":"Shangani",
    "qs:photos_9r":0,
    "qs:photos_sr":0,
    "qs:pop_sr":"4",
    "wd:wordcount":54,
    "wof:name":"Shangani",
    "wof:placetype":"locality",
    "wof:population":3835
},
  "geometry": {"coordinates":[29.36667,-19.78333],"type":"Point"}
}