{
  "type": "Feature",
  "properties": {
    "gn:country":"ZW",
    "gn:fcode":"PPL",
    "gn:population":3835,
    "iso:country":"ZW",
    "name:ara_x_preferred":[
        "\u0634\u0627\u0646\u063a\u0627\u0646\u064a"
    ],
    "name:ben_x_preferred":[
        "\u09b6\u09be\u0999\u09cd\u0997\u09be\u09a8\u09bf"
    ],
    "name:ell_x_preferred":[
        "\u03a3\u03b1\u03bd\u03b3\u03ba\u03b1\u03bd\u03af"
    ],
    "name:eng_x_preferred":[
        "Shangani"
    ],
    "name:fas_x_preferred":[
        "\u0634\u0627\u0646\u06af\u0627\u0646\u06cc"
    ],
    "name:heb_x_preferred":[
        "\u05e9\u05e0\u05d2\u05d0\u05e0\u05d9"
    ],
    "name:hun_x_preferred":[
        "Shangani"
    ],
    "name:ind_x_preferred":[
        "Shangani"
    ],
    "name:ita_x_preferred":[
        "Shangani"
    ],
    "name:jpn_x_preferred":[
        "\u30b7\u30e3\u30f3\u30ac\u30cb\u5ddd"
    ],
    "name:kor_x_preferred":[
        "\uc0f9\uac00\ub2c8"
    ],
    "name:nld_x_preferred":[
        "Shangani"
    ],
    "name:pol_x_preferred":[
        "Shangani"
    ],
    "name:por_x_preferred":[
        "Shangani"
    ],
    "name:rus_x_preferred":[
        "\u0428\u0430\u043d\u0433\u0430\u043d\u0438"
    ],
    "name:spa_x_preferred":[
        "Shangani"
    ],
    "name:swe_x_preferred":[
        "Shangani"
    ],
    "name:tur_x_preferred":[
        "Shangani"
    ],
    "name:ukr_x_preferred":[
        "\u0428\u0435\u043d\u0433\u0430\u043d\u0456"
    ],
    "name:urd_x_preferred":[
        "\u0634\u0627\u0646\u06af\u0627\u0646\u06cc"
    ],
    "name:vie_x_preferred":[
        "S\u00f4ng Shangani"
    ],
    "name:zho_cn_x_preferred":[
        "\u5c1a\u52a0\u5c3c\u6cb3"
    ],
    "name:zho_tw_x_preferred":[
        "\u5c1a\u52a0\u5c3c\u6cb3"
    ],
    "name:zul_x_preferred":[
        "Shangani"
    ],
    "qs:name":"Shangani",
    "qs:photos_9r":0,
    "qs:photos_sr":0,
    "qs:pop_sr":"4",
    "wd:wordcount":54,
    "wof:name":"Shangani",
    "wof:placetype":"locality",
    "wof:population":3835
},
  "geometry": {"coordinates":[29.36667,-19.78333],"type":"Point"}
}