{
  "type": "Feature",
  "properties": {
    "gn:admin1_code":"08",
    "gn:asciiname":"Gwema",
    "gn:country_code":"ZW",
    "gn:dem":841,
    "gn:feature_class":"P",
    "gn:feature_code":"PPL",
    "gn:name":"Gwema",
    "gn:population":0,
    "gn:timezone":"Africa/Harare",
    "iso:country":"ZW",
    "wof:name":"Gwema",
    "wof:placetype":"locality"
},
  "geometry": {"coordinates":[31.81709,-19.9536],"type":"Point"}
}