{
  "type": "Feature",
  "properties": {
    "gn:admin1_code":"8.0",
    "gn:admin2_code":"893482.0",
    "gn:asciiname":"Triangle",
    "gn:country_code":"ZW",
    "gn:dem":412,
    "gn:feature_class":"P",
    "gn:feature_code":"PPL",
    "gn:name":"Triangle",
    "gn:population":0,
    "gn:timezone":"Africa/Harare",
    "iso:country":"ZW",
    "name:deu_x_preferred":[
        "Triangle"
    ],
    "name:eng_x_preferred":[
        "Triangle"
    ],
    "wof:name":"Triangle",
    "wof:placetype":"locality"
},
  "geometry": {"coordinates":[31.45,-21.03333],"type":"Point"}
}