{
  "type": "Feature",
  "properties": {
    "gn:admin1_code":"6.0",
    "gn:asciiname":"Mangutana",
    "gn:country_code":"ZW",
    "gn:dem":1020,
    "gn:feature_class":"P",
    "gn:feature_code":"PPL",
    "gn:name":"Mangutana",
    "gn:population":0,
    "gn:timezone":"Africa/Harare",
    "iso:country":"ZW",
    "wof:name":"Mangutana",
    "wof:placetype":"locality"
},
  "geometry": {"coordinates":[27.35015,-19.38362],"type":"Point"}
}