{
  "type": "Feature",
  "properties": {
    "gn:admin1_code":"1.0",
    "gn:asciiname":"Madioma",
    "gn:country_code":"ZW",
    "gn:dem":1937,
    "gn:feature_class":"P",
    "gn:feature_code":"PPL",
    "gn:name":"Madioma",
    "gn:population":0,
    "gn:timezone":"Africa/Harare",
    "iso:country":"ZW",
    "wof:name":"Madioma",
    "wof:placetype":"locality"
},
  "geometry": {"coordinates":[32.76667,-17.81667000000001],"type":"Point"}
}