{
  "type": "Feature",
  "properties": {
    "gn:admin1_code":"6.0",
    "gn:asciiname":"Chief Sikobokobo",
    "gn:country_code":"ZW",
    "gn:dem":1022,
    "gn:feature_class":"P",
    "gn:feature_code":"PPL",
    "gn:name":"Chief Sikobokobo",
    "gn:population":0,
    "gn:timezone":"Africa/Harare",
    "iso:country":"ZW",
    "name:eng_x_preferred":[
        "Chief Sikobokobo"
    ],
    "wof:name":"Chief Sikobokobo",
    "wof:placetype":"locality"
},
  "geometry": {"coordinates":[28.4937,-18.75764],"type":"Point"}
}