{
  "type": "Feature",
  "properties": {
    "gn:admin1_code":"4.0",
    "gn:asciiname":"Mafuto",
    "gn:country_code":"ZW",
    "gn:dem":436,
    "gn:feature_class":"P",
    "gn:feature_code":"PPL",
    "gn:name":"Mafuto",
    "gn:population":0,
    "gn:timezone":"Africa/Harare",
    "iso:country":"ZW",
    "wof:name":"Mafuto",
    "wof:placetype":"locality"
},
  "geometry": {"coordinates":[32.76667,-16.71667],"type":"Point"}
}