{
  "type": "Feature",
  "properties": {
    "gn:admin1_code":"6.0",
    "gn:asciiname":"Zuzumba",
    "gn:country_code":"ZW",
    "gn:dem":1174,
    "gn:feature_class":"P",
    "gn:feature_code":"PPL",
    "gn:name":"Zuzumba",
    "gn:population":0,
    "gn:timezone":"Africa/Harare",
    "iso:country":"ZW",
    "wof:name":"Zuzumba",
    "wof:placetype":"locality"
},
  "geometry": {"coordinates":[27.93333,-20.03333],"type":"Point"}
}