{
  "type": "Feature",
  "properties": {
    "gn:admin1_code":"1.0",
    "gn:asciiname":"Makamure",
    "gn:country_code":"ZW",
    "gn:dem":962,
    "gn:feature_class":"P",
    "gn:feature_code":"PPL",
    "gn:name":"Makamure",
    "gn:population":0,
    "gn:timezone":"Africa/Harare",
    "iso:country":"ZW",
    "wof:name":"Makamure",
    "wof:placetype":"locality"
},
  "geometry": {"coordinates":[31.70996,-19.165],"type":"Point"}
}