{
  "type": "Feature",
  "properties": {
    "gn:admin1_code":"6.0",
    "gn:asciiname":"Tamhla",
    "gn:cc2":"ZW",
    "gn:country_code":"ZW",
    "gn:dem":997,
    "gn:feature_class":"P",
    "gn:feature_code":"PPL",
    "gn:name":"Tamhla",
    "gn:population":0,
    "gn:timezone":"Africa/Harare",
    "iso:country":"ZW",
    "name:und_x_variant":[
        "Tamuhle",
        "Tamhla"
    ],
    "wof:name":"Tamhla",
    "wof:placetype":"locality"
},
  "geometry": {"coordinates":[27.68333,-19.31667],"type":"Point"}
}