{
  "type": "Feature",
  "properties": {
    "gn:admin1_code":"08",
    "gn:asciiname":"Magwiro",
    "gn:country_code":"ZW",
    "gn:dem":900,
    "gn:feature_class":"P",
    "gn:feature_code":"PPL",
    "gn:name":"Magwiro",
    "gn:population":0,
    "gn:timezone":"Africa/Harare",
    "iso:country":"ZW",
    "wof:name":"Magwiro",
    "wof:placetype":"locality"
},
  "geometry": {"coordinates":[31.66414,-19.85591],"type":"Point"}
}