{
  "type": "Feature",
  "properties": {
    "gn:admin1_code":"6.0",
    "gn:asciiname":"Tsholotsho",
    "gn:country_code":"ZW",
    "gn:dem":1090,
    "gn:feature_class":"P",
    "gn:feature_code":"PPL",
    "gn:name":"Tsholotsho",
    "gn:population":0,
    "gn:timezone":"Africa/Harare",
    "iso:country":"ZW",
    "name:bar_x_preferred":[
        "Tsholotsho"
    ],
    "name:por_x_preferred":[
        "Tsholotsho"
    ],
    "name:und_x_variant":[
        "Tjolotjo",
        "Shololezhou"
    ],
    "wof:name":"Tsholotsho",
    "wof:placetype":"locality"
},
  "geometry": {"coordinates":[27.76508,-19.75562],"type":"Point"}
}