{
  "type": "Feature",
  "properties": {
    "gn:admin1_code":"7.0",
    "gn:asciiname":"Lutombe",
    "gn:country_code":"ZW",
    "gn:dem":557,
    "gn:feature_class":"P",
    "gn:feature_code":"PPL",
    "gn:name":"Lutombe",
    "gn:population":0,
    "gn:timezone":"Africa/Harare",
    "iso:country":"ZW",
    "wof:name":"Lutombe",
    "wof:placetype":"locality"
},
  "geometry": {"coordinates":[30.15,-22.08333],"type":"Point"}
}