{
  "type": "Feature",
  "properties": {
    "gn:admin1_code":"4.0",
    "gn:asciiname":"Gwavava",
    "gn:country_code":"ZW",
    "gn:dem":1298,
    "gn:feature_class":"P",
    "gn:feature_code":"PPL",
    "gn:name":"Gwavava",
    "gn:population":0,
    "gn:timezone":"Africa/Harare",
    "iso:country":"ZW",
    "wof:name":"Gwavava",
    "wof:placetype":"locality"
},
  "geometry": {"coordinates":[31.52314,-18.86159],"type":"Point"}
}