{
  "type": "Feature",
  "properties": {
    "gn:admin1_code":"08",
    "gn:asciiname":"Panichi",
    "gn:country_code":"ZW",
    "gn:dem":867,
    "gn:feature_class":"P",
    "gn:feature_code":"PPL",
    "gn:name":"Panichi",
    "gn:population":0,
    "gn:timezone":"Africa/Harare",
    "iso:country":"ZW",
    "wof:name":"Panichi",
    "wof:placetype":"locality"
},
  "geometry": {"coordinates":[31.82488,-19.96265],"type":"Point"}
}