{
  "type": "Feature",
  "properties": {
    "gn:admin1_code":"8.0",
    "gn:asciiname":"Muvuti",
    "gn:country_code":"ZW",
    "gn:dem":1029,
    "gn:feature_class":"P",
    "gn:feature_code":"PPL",
    "gn:name":"Muvuti",
    "gn:population":0,
    "gn:timezone":"Africa/Harare",
    "iso:country":"ZW",
    "wof:name":"Muvuti",
    "wof:placetype":"locality"
},
  "geometry": {"coordinates":[31.63611,-19.93611],"type":"Point"}
}