{
  "type": "Feature",
  "properties": {
    "gn:admin1_code":"6.0",
    "gn:asciiname":"Jakalazi",
    "gn:country_code":"ZW",
    "gn:dem":1022,
    "gn:feature_class":"P",
    "gn:feature_code":"PPL",
    "gn:name":"Jakalazi",
    "gn:population":0,
    "gn:timezone":"Africa/Harare",
    "iso:country":"ZW",
    "name:und_x_variant":[
        "Jakalasi"
    ],
    "wof:name":"Jakalazi",
    "wof:placetype":"locality"
},
  "geometry": {"coordinates":[27.55473,-19.25233],"type":"Point"}
}