{
  "type": "Feature",
  "properties": {
    "gn:admin1_code":"08",
    "gn:asciiname":"Maibire",
    "gn:country_code":"ZW",
    "gn:dem":961,
    "gn:feature_class":"P",
    "gn:feature_code":"PPL",
    "gn:name":"Maibire",
    "gn:population":0,
    "gn:timezone":"Africa/Harare",
    "iso:country":"ZW",
    "wof:name":"Maibire",
    "wof:placetype":"locality"
},
  "geometry": {"coordinates":[31.69194,-19.67914],"type":"Point"}
}