{
  "type": "Feature",
  "properties": {
    "gn:admin1_code":"08",
    "gn:asciiname":"Chaurura",
    "gn:country_code":"ZW",
    "gn:dem":1076,
    "gn:feature_class":"P",
    "gn:feature_code":"PPL",
    "gn:name":"Chaurura",
    "gn:population":0,
    "gn:timezone":"Africa/Harare",
    "iso:country":"ZW",
    "wof:name":"Chaurura",
    "wof:placetype":"locality"
},
  "geometry": {"coordinates":[31.67002,-19.96567000000001],"type":"Point"}
}