{
  "type": "Feature",
  "properties": {
    "gn:admin1_code":"6.0",
    "gn:asciiname":"Emabandeni",
    "gn:country_code":"ZW",
    "gn:dem":982,
    "gn:feature_class":"P",
    "gn:feature_code":"PPL",
    "gn:name":"Emabandeni",
    "gn:population":0,
    "gn:timezone":"Africa/Harare",
    "iso:country":"ZW",
    "wof:name":"Emabandeni",
    "wof:placetype":"locality"
},
  "geometry": {"coordinates":[27.68352,-19.15128],"type":"Point"}
}