{
  "type": "Feature",
  "properties": {
    "gn:admin1_code":"08",
    "gn:asciiname":"Chamisa",
    "gn:country_code":"ZW",
    "gn:dem":1107,
    "gn:feature_class":"P",
    "gn:feature_code":"PPL",
    "gn:name":"Chamisa",
    "gn:population":0,
    "gn:timezone":"Africa/Harare",
    "iso:country":"ZW",
    "wof:name":"Chamisa",
    "wof:placetype":"locality"
},
  "geometry": {"coordinates":[31.55026,-19.95248],"type":"Point"}
}