{
  "type": "Feature",
  "properties": {
    "gn:admin1_code":"6.0",
    "gn:asciiname":"Shaba",
    "gn:country_code":"ZW",
    "gn:dem":1206,
    "gn:feature_class":"P",
    "gn:feature_code":"PPL",
    "gn:name":"Shaba",
    "gn:population":0,
    "gn:timezone":"Africa/Harare",
    "iso:country":"ZW",
    "name:bar_x_preferred":[
        "Shaba"
    ],
    "name:ceb_x_preferred":[
        "Shaba"
    ],
    "name:deu_x_preferred":[
        "Shaba"
    ],
    "name:ita_x_preferred":[
        "Shaba"
    ],
    "name:swe_x_preferred":[
        "Shaba"
    ],
    "wof:name":"Shaba",
    "wof:placetype":"locality"
},
  "geometry": {"coordinates":[27.76667,-20.05],"type":"Point"}
}