{
  "type": "Feature",
  "properties": {
    "gn:admin1_code":"6.0",
    "gn:asciiname":"Kapane",
    "gn:country_code":"ZW",
    "gn:dem":1020,
    "gn:feature_class":"P",
    "gn:feature_code":"PPL",
    "gn:name":"Kapane",
    "gn:population":0,
    "gn:timezone":"Africa/Harare",
    "iso:country":"ZW",
    "wof:name":"Kapane",
    "wof:placetype":"locality"
},
  "geometry": {"coordinates":[27.51855,-19.25113],"type":"Point"}
}