{
  "type": "Feature",
  "properties": {
    "gn:admin1_code":"5.0",
    "gn:asciiname":"Chasauka",
    "gn:country_code":"ZW",
    "gn:dem":1055,
    "gn:feature_class":"P",
    "gn:feature_code":"PPL",
    "gn:name":"Chasauka",
    "gn:population":0,
    "gn:timezone":"Africa/Harare",
    "iso:country":"ZW",
    "name:eng_x_preferred":[
        "Chasauka"
    ],
    "wof:name":"Chasauka",
    "wof:placetype":"locality"
},
  "geometry": {"coordinates":[29.27902000000001,-16.94447000000001],"type":"Point"}
}