{
  "type": "Feature",
  "properties": {
    "gn:admin1_code":"08",
    "gn:asciiname":"Muzorori",
    "gn:country_code":"ZW",
    "gn:dem":1033,
    "gn:feature_class":"P",
    "gn:feature_code":"PPL",
    "gn:name":"Muzorori",
    "gn:population":0,
    "gn:timezone":"Africa/Harare",
    "iso:country":"ZW",
    "wof:name":"Muzorori",
    "wof:placetype":"locality"
},
  "geometry": {"coordinates":[31.52024,-19.73314],"type":"Point"}
}