{
  "type": "Feature",
  "properties": {
    "gn:admin1_code":"02",
    "gn:asciiname":"Siamwanja",
    "gn:country_code":"ZW",
    "gn:dem":899,
    "gn:feature_class":"P",
    "gn:feature_code":"PPL",
    "gn:name":"Siamwanja",
    "gn:population":0,
    "gn:timezone":"Africa/Harare",
    "iso:country":"ZW",
    "wof:name":"Siamwanja",
    "wof:placetype":"locality"
},
  "geometry": {"coordinates":[29.26772,-18.20637],"type":"Point"}
}