{
  "type": "Feature",
  "properties": {
    "gn:admin1_code":"08",
    "gn:asciiname":"Chapungu",
    "gn:country_code":"ZW",
    "gn:dem":942,
    "gn:feature_class":"P",
    "gn:feature_code":"PPL",
    "gn:name":"Chapungu",
    "gn:population":0,
    "gn:timezone":"Africa/Harare",
    "iso:country":"ZW",
    "wof:name":"Chapungu",
    "wof:placetype":"locality"
},
  "geometry": {"coordinates":[31.86617,-19.90404],"type":"Point"}
}