{
  "type": "Feature",
  "properties": {
    "gn:admin1_code":"6.0",
    "gn:asciiname":"Zabagwadi",
    "gn:country_code":"ZW",
    "gn:dem":1058,
    "gn:feature_class":"P",
    "gn:feature_code":"PPL",
    "gn:name":"Zabagwadi",
    "gn:population":0,
    "gn:timezone":"Africa/Harare",
    "iso:country":"ZW",
    "wof:name":"Zabagwadi",
    "wof:placetype":"locality"
},
  "geometry": {"coordinates":[27.74035,-19.58424],"type":"Point"}
}