{
  "type": "Feature",
  "properties": {
    "gn:admin1_code":"4.0",
    "gn:asciiname":"Mugweni-Zanje",
    "gn:country_code":"ZW",
    "gn:dem":1131,
    "gn:feature_class":"P",
    "gn:feature_code":"PPL",
    "gn:name":"Mugweni-Zanje",
    "gn:population":0,
    "gn:timezone":"Africa/Harare",
    "iso:country":"ZW",
    "wof:name":"Mugweni-Zanje",
    "wof:placetype":"locality"
},
  "geometry": {"coordinates":[31.51095,-19.13863],"type":"Point"}
}