{
  "type": "Feature",
  "properties": {
    "gn:admin1_code":"6.0",
    "gn:asciiname":"Salankomo",
    "gn:country_code":"ZW",
    "gn:dem":993,
    "gn:feature_class":"P",
    "gn:feature_code":"PPL",
    "gn:name":"Salankomo",
    "gn:population":0,
    "gn:timezone":"Africa/Harare",
    "iso:country":"ZW",
    "wof:name":"Salankomo",
    "wof:placetype":"locality"
},
  "geometry": {"coordinates":[27.05351,-19.54363],"type":"Point"}
}