{
  "type": "Feature",
  "properties": {
    "gn:admin1_code":"08",
    "gn:asciiname":"Ndakaripei",
    "gn:country_code":"ZW",
    "gn:dem":1012,
    "gn:feature_class":"P",
    "gn:feature_code":"PPL",
    "gn:name":"Ndakaripei",
    "gn:population":0,
    "gn:timezone":"Africa/Harare",
    "iso:country":"ZW",
    "wof:name":"Ndakaripei",
    "wof:placetype":"locality"
},
  "geometry": {"coordinates":[31.63412000000001,-19.68914],"type":"Point"}
}