{
  "type": "Feature",
  "properties": {
    "gn:admin1_code":"5.0",
    "gn:asciiname":"Muchidzagora",
    "gn:country_code":"ZW",
    "gn:dem":1143,
    "gn:feature_class":"P",
    "gn:feature_code":"PPL",
    "gn:name":"Muchidzagora",
    "gn:population":0,
    "gn:timezone":"Africa/Harare",
    "iso:country":"ZW",
    "name:eng_x_preferred":[
        "Muchidzagora"
    ],
    "wof:name":"Muchidzagora",
    "wof:placetype":"locality"
},
  "geometry": {"coordinates":[29.36689,-16.84246],"type":"Point"}
}