{
  "type": "Feature",
  "properties": {
    "gn:admin1_code":"5.0",
    "gn:asciiname":"Kamhali",
    "gn:country_code":"ZW",
    "gn:dem":920,
    "gn:feature_class":"P",
    "gn:feature_code":"PPL",
    "gn:name":"Kamhali",
    "gn:population":0,
    "gn:timezone":"Africa/Harare",
    "iso:country":"ZW",
    "name:eng_x_preferred":[
        "Kamhali"
    ],
    "wof:name":"Kamhali",
    "wof:placetype":"locality"
},
  "geometry": {"coordinates":[29.20715,-16.73324],"type":"Point"}
}