{
  "type": "Feature",
  "properties": {
    "gn:admin1_code":"08",
    "gn:asciiname":"Guni",
    "gn:country_code":"ZW",
    "gn:dem":941,
    "gn:feature_class":"P",
    "gn:feature_code":"PPL",
    "gn:name":"Guni",
    "gn:population":0,
    "gn:timezone":"Africa/Harare",
    "iso:country":"ZW",
    "wof:name":"Guni",
    "wof:placetype":"locality"
},
  "geometry": {"coordinates":[31.76484,-19.97647000000001],"type":"Point"}
}