{
  "type": "Feature",
  "properties": {
    "gn:admin1_code":"1.0",
    "gn:asciiname":"Kudiwa",
    "gn:country_code":"ZW",
    "gn:dem":1102,
    "gn:feature_class":"P",
    "gn:feature_code":"PPL",
    "gn:name":"Kudiwa",
    "gn:population":0,
    "gn:timezone":"Africa/Harare",
    "iso:country":"ZW",
    "wof:name":"Kudiwa",
    "wof:placetype":"locality"
},
  "geometry": {"coordinates":[32.53615,-18.80358],"type":"Point"}
}