{
  "type": "Feature",
  "properties": {
    "gn:admin1_code":"08",
    "gn:asciiname":"Mudzimbabwe",
    "gn:country_code":"ZW",
    "gn:dem":866,
    "gn:feature_class":"P",
    "gn:feature_code":"PPL",
    "gn:name":"Mudzimbabwe",
    "gn:population":0,
    "gn:timezone":"Africa/Harare",
    "iso:country":"ZW",
    "wof:name":"Mudzimbabwe",
    "wof:placetype":"locality"
},
  "geometry": {"coordinates":[31.7588,-19.81764],"type":"Point"}
}