{
  "type": "Feature",
  "properties": {
    "gn:admin1_code":"6.0",
    "gn:asciiname":"Chief Nkalakata",
    "gn:country_code":"ZW",
    "gn:dem":1153,
    "gn:feature_class":"P",
    "gn:feature_code":"PPL",
    "gn:name":"Chief Nkalakata",
    "gn:population":0,
    "gn:timezone":"Africa/Harare",
    "iso:country":"ZW",
    "wof:name":"Chief Nkalakata",
    "wof:placetype":"locality"
},
  "geometry": {"coordinates":[28.94808,-19.04385],"type":"Point"}
}