{
  "type": "Feature",
  "properties": {
    "gn:admin1_code":"6.0",
    "gn:asciiname":"Tshibizina",
    "gn:country_code":"ZW",
    "gn:dem":1016,
    "gn:feature_class":"P",
    "gn:feature_code":"PPL",
    "gn:name":"Tshibizina",
    "gn:population":0,
    "gn:timezone":"Africa/Harare",
    "iso:country":"ZW",
    "name:und_x_variant":[
        "Tshibizena",
        "Tshibizina"
    ],
    "wof:name":"Tshibizina",
    "wof:placetype":"locality"
},
  "geometry": {"coordinates":[27.28307,-19.52014],"type":"Point"}
}