{
  "type": "Feature",
  "properties": {
    "gn:admin1_code":"3.0",
    "gn:asciiname":"Amandas",
    "gn:cc2":"ZW",
    "gn:country_code":"ZW",
    "gn:dem":1262,
    "gn:feature_class":"P",
    "gn:feature_code":"PPL",
    "gn:name":"Amandas",
    "gn:population":0,
    "gn:timezone":"Africa/Harare",
    "iso:country":"ZW",
    "name:und_x_variant":[
        "Mhanda",
        "Amandas"
    ],
    "wof:name":"Amandas",
    "wof:placetype":"locality"
},
  "geometry": {"coordinates":[30.95,-17.36667000000001],"type":"Point"}
}