{
  "type": "Feature",
  "properties": {
    "gn:admin1_code":"5.0",
    "gn:asciiname":"Milan",
    "gn:country_code":"ZW",
    "gn:dem":1140,
    "gn:feature_class":"P",
    "gn:feature_code":"PPL",
    "gn:name":"Milan",
    "gn:population":0,
    "gn:timezone":"Africa/Harare",
    "iso:country":"ZW",
    "wof:name":"Milan",
    "wof:placetype":"locality"
},
  "geometry": {"coordinates":[29.91667,-18.13333],"type":"Point"}
}