{
  "type": "Feature",
  "properties": {
    "gn:admin1_code":"08",
    "gn:asciiname":"Chigavade",
    "gn:country_code":"ZW",
    "gn:dem":1021,
    "gn:feature_class":"P",
    "gn:feature_code":"PPL",
    "gn:name":"Chigavade",
    "gn:population":0,
    "gn:timezone":"Africa/Harare",
    "iso:country":"ZW",
    "wof:name":"Chigavade",
    "wof:placetype":"locality"
},
  "geometry": {"coordinates":[31.71703,-19.92405],"type":"Point"}
}