{
  "type": "Feature",
  "properties": {
    "gn:admin1_code":"6.0",
    "gn:asciiname":"Semawuru",
    "gn:country_code":"ZW",
    "gn:dem":1005,
    "gn:feature_class":"P",
    "gn:feature_code":"PPL",
    "gn:name":"Semawuru",
    "gn:population":0,
    "gn:timezone":"Africa/Harare",
    "iso:country":"ZW",
    "wof:name":"Semawuru",
    "wof:placetype":"locality"
},
  "geometry": {"coordinates":[27.19263,-19.48457],"type":"Point"}
}