{
  "type": "Feature",
  "properties": {
    "gn:admin1_code":"6.0",
    "gn:asciiname":"Hunts Road Halt",
    "gn:country_code":"ZW",
    "gn:dem":1284,
    "gn:feature_class":"P",
    "gn:feature_code":"PPL",
    "gn:name":"Hunts Road Halt",
    "gn:population":0,
    "gn:timezone":"Africa/Harare",
    "iso:country":"ZW",
    "wof:name":"Hunts Road Halt",
    "wof:placetype":"locality"
},
  "geometry": {"coordinates":[28.76667,-19.76667],"type":"Point"}
}