{
  "type": "Feature",
  "properties": {
    "gn:admin1_code":"4.0",
    "gn:asciiname":"Zimondi",
    "gn:country_code":"ZW",
    "gn:dem":1281,
    "gn:feature_class":"P",
    "gn:feature_code":"PPL",
    "gn:name":"Zimondi",
    "gn:population":0,
    "gn:timezone":"Africa/Harare",
    "iso:country":"ZW",
    "wof:name":"Zimondi",
    "wof:placetype":"locality"
},
  "geometry": {"coordinates":[31.45401,-18.77169],"type":"Point"}
}