{
  "type": "Feature",
  "properties": {
    "gn:country":"ZW",
    "gn:fcode":"PPL",
    "gn:pop":2228,
    "iso:country":"ZW",
    "name:afr_x_preferred":[
        "Esigodini"
    ],
    "name:bar_x_preferred":[
        "Esigodini"
    ],
    "name:bul_x_preferred":[
        "\u0415\u0441\u0438\u0433\u043e\u0434\u0438\u043d\u0438"
    ],
    "name:cat_x_preferred":[
        "Esigodini"
    ],
    "name:ceb_x_preferred":[
        "Esigodini"
    ],
    "name:deu_x_preferred":[
        "Esigodini"
    ],
    "name:eng_x_preferred":[
        "Esigodini"
    ],
    "name:ita_x_preferred":[
        "Esigodini"
    ],
    "name:ltz_x_preferred":[
        "Esigodini"
    ],
    "name:nld_x_preferred":[
        "Esigodini"
    ],
    "name:unk_x_variant":[
        "Essexvale"
    ],
    "qs:name":"Esigodini",
    "qs:photos_9r":0,
    "qs:photos_sr":0,
    "qs:pop_sr":"4",
    "wd:wordcount":200,
    "wof:name":"Esigodini",
    "wof:placetype":"locality",
    "wof:population":2228
},
  "geometry": {"coordinates":[28.92261,-20.28979],"type":"Point"}
}