{
  "type": "Feature",
  "properties": {
    "gn:admin1_code":"2.0",
    "gn:asciiname":"Chief Chilimanzi",
    "gn:country_code":"ZW",
    "gn:dem":1398,
    "gn:feature_class":"P",
    "gn:feature_code":"PPL",
    "gn:name":"Chief Chilimanzi",
    "gn:population":0,
    "gn:timezone":"Africa/Harare",
    "iso:country":"ZW",
    "wof:name":"Chief Chilimanzi",
    "wof:placetype":"locality"
},
  "geometry": {"coordinates":[30.65269,-19.5357],"type":"Point"}
}