{
  "type": "Feature",
  "properties": {
    "gn:admin1_code":"08",
    "gn:asciiname":"Guzha",
    "gn:country_code":"ZW",
    "gn:dem":889,
    "gn:feature_class":"P",
    "gn:feature_code":"PPL",
    "gn:name":"Guzha",
    "gn:population":0,
    "gn:timezone":"Africa/Harare",
    "iso:country":"ZW",
    "wof:name":"Guzha",
    "wof:placetype":"locality"
},
  "geometry": {"coordinates":[31.79454,-19.65102000000001],"type":"Point"}
}