{
  "type": "Feature",
  "properties": {
    "gn:admin1_code":"08",
    "gn:asciiname":"Panganai",
    "gn:country_code":"ZW",
    "gn:dem":944,
    "gn:feature_class":"P",
    "gn:feature_code":"PPL",
    "gn:name":"Panganai",
    "gn:population":0,
    "gn:timezone":"Africa/Harare",
    "iso:country":"ZW",
    "wof:name":"Panganai",
    "wof:placetype":"locality"
},
  "geometry": {"coordinates":[31.5995,-19.87593],"type":"Point"}
}