{
  "type": "Feature",
  "properties": {
    "gn:admin1_code":"08",
    "gn:asciiname":"Hapanyengwi",
    "gn:country_code":"ZW",
    "gn:dem":1014,
    "gn:feature_class":"P",
    "gn:feature_code":"PPL",
    "gn:name":"Hapanyengwi",
    "gn:population":0,
    "gn:timezone":"Africa/Harare",
    "iso:country":"ZW",
    "wof:name":"Hapanyengwi",
    "wof:placetype":"locality"
},
  "geometry": {"coordinates":[31.62888,-19.72472],"type":"Point"}
}