{
  "type": "Feature",
  "properties": {
    "gn:admin1_code":"2.0",
    "gn:asciiname":"Rupepwe",
    "gn:country_code":"ZW",
    "gn:dem":1200,
    "gn:feature_class":"P",
    "gn:feature_code":"PPL",
    "gn:name":"Rupepwe",
    "gn:population":0,
    "gn:timezone":"Africa/Harare",
    "iso:country":"ZW",
    "wof:name":"Rupepwe",
    "wof:placetype":"locality"
},
  "geometry": {"coordinates":[30.66667,-19.73333],"type":"Point"}
}