{
  "type": "Feature",
  "properties": {
    "gn:admin1_code":"5.0",
    "gn:asciiname":"Mazivakufa",
    "gn:country_code":"ZW",
    "gn:dem":1275,
    "gn:feature_class":"P",
    "gn:feature_code":"PPLL",
    "gn:name":"Mazivakufa",
    "gn:population":0,
    "gn:timezone":"Africa/Harare",
    "iso:country":"ZW",
    "wof:name":"Mazivakufa",
    "wof:placetype":"locality"
},
  "geometry": {"coordinates":[30.67683,-18.24295],"type":"Point"}
}