{
  "type": "Feature",
  "properties": {
    "gn:admin1_code":"8.0",
    "gn:asciiname":"Kefas",
    "gn:country_code":"ZW",
    "gn:dem":1075,
    "gn:feature_class":"P",
    "gn:feature_code":"PPL",
    "gn:name":"Kefas",
    "gn:population":0,
    "gn:timezone":"Africa/Harare",
    "iso:country":"ZW",
    "wof:name":"Kefas",
    "wof:placetype":"locality"
},
  "geometry": {"coordinates":[31.55264,-19.49473],"type":"Point"}
}