{
  "type": "Feature",
  "properties": {
    "gn:admin1_code":"1.0",
    "gn:asciiname":"Chimhawu",
    "gn:country_code":"ZW",
    "gn:dem":1029,
    "gn:feature_class":"P",
    "gn:feature_code":"PPL",
    "gn:name":"Chimhawu",
    "gn:population":0,
    "gn:timezone":"Africa/Harare",
    "iso:country":"ZW",
    "wof:name":"Chimhawu",
    "wof:placetype":"locality"
},
  "geometry": {"coordinates":[31.66064,-19.19391],"type":"Point"}
}