{
  "type": "Feature",
  "properties": {
    "gn:admin1_code":"3.0",
    "gn:asciiname":"Chief Matsiwo",
    "gn:country_code":"ZW",
    "gn:dem":396,
    "gn:feature_class":"P",
    "gn:feature_code":"PPL",
    "gn:name":"Chief Matsiwo",
    "gn:population":0,
    "gn:timezone":"Africa/Harare",
    "iso:country":"ZW",
    "name:eng_x_preferred":[
        "Chief Matsiwo"
    ],
    "wof:name":"Chief Matsiwo",
    "wof:placetype":"locality"
},
  "geometry": {"coordinates":[30.90897,-16.30339],"type":"Point"}
}