{
  "type": "Feature",
  "properties": {
    "gn:admin1_code":"3.0",
    "gn:asciiname":"Muringai",
    "gn:country_code":"ZW",
    "gn:dem":1216,
    "gn:feature_class":"P",
    "gn:feature_code":"PPL",
    "gn:name":"Muringai",
    "gn:population":0,
    "gn:timezone":"Africa/Harare",
    "iso:country":"ZW",
    "name:eng_x_preferred":[
        "Muringai"
    ],
    "wof:name":"Muringai",
    "wof:placetype":"locality"
},
  "geometry": {"coordinates":[31.11787,-17.13622],"type":"Point"}
}