{
  "type": "Feature",
  "properties": {
    "gn:admin1_code":"6.0",
    "gn:asciiname":"Sontamba",
    "gn:country_code":"ZW",
    "gn:dem":1080,
    "gn:feature_class":"P",
    "gn:feature_code":"PPL",
    "gn:name":"Sontamba",
    "gn:population":0,
    "gn:timezone":"Africa/Harare",
    "iso:country":"ZW",
    "name:und_x_variant":[
        "Sontambo",
        "Sontamba"
    ],
    "wof:name":"Sontamba",
    "wof:placetype":"locality"
},
  "geometry": {"coordinates":[27.6416,-19.76708],"type":"Point"}
}