{
  "type": "Feature",
  "properties": {
    "gn:admin1_code":"7.0",
    "gn:asciiname":"Fresnaye",
    "gn:country_code":"ZW",
    "gn:dem":1439,
    "gn:feature_class":"P",
    "gn:feature_code":"PPLL",
    "gn:name":"Fresnaye",
    "gn:population":0,
    "gn:timezone":"Africa/Harare",
    "iso:country":"ZW",
    "wof:name":"Fresnaye",
    "wof:placetype":"locality"
},
  "geometry": {"coordinates":[28.74611,-20.23722],"type":"Point"}
}