{
  "type": "Feature",
  "properties": {
    "gn:admin1_code":"5.0",
    "gn:asciiname":"Gukwe",
    "gn:country_code":"ZW",
    "gn:dem":1326,
    "gn:feature_class":"P",
    "gn:feature_code":"PPL",
    "gn:name":"Gukwe",
    "gn:population":0,
    "gn:timezone":"Africa/Harare",
    "iso:country":"ZW",
    "wof:name":"Gukwe",
    "wof:placetype":"locality"
},
  "geometry": {"coordinates":[30.71082,-18.14525],"type":"Point"}
}