{
  "type": "Feature",
  "properties": {
    "gn:admin1_code":"4.0",
    "gn:asciiname":"Gondo",
    "gn:country_code":"ZW",
    "gn:dem":1560,
    "gn:feature_class":"P",
    "gn:feature_code":"PPL",
    "gn:name":"Gondo",
    "gn:population":0,
    "gn:timezone":"Africa/Harare",
    "iso:country":"ZW",
    "name:ceb_x_preferred":[
        "Gondo"
    ],
    "name:nld_x_preferred":[
        "Gondo"
    ],
    "name:swe_x_preferred":[
        "Gondo"
    ],
    "wof:name":"Gondo",
    "wof:placetype":"locality"
},
  "geometry": {"coordinates":[31.0499,-18.89041],"type":"Point"}
}