{
  "type": "Feature",
  "properties": {
    "gn:admin1_code":"10.0",
    "gn:asciiname":"Stortford",
    "gn:country_code":"ZW",
    "gn:dem":1461,
    "gn:feature_class":"P",
    "gn:feature_code":"PPL",
    "gn:name":"Stortford",
    "gn:population":0,
    "gn:timezone":"Africa/Harare",
    "iso:country":"ZW",
    "name:eng_x_preferred":[
        "Stortford"
    ],
    "wof:name":"Stortford",
    "wof:placetype":"locality"
},
  "geometry": {"coordinates":[30.96556,-17.79778],"type":"Point"}
}