{
  "type": "Feature",
  "properties": {
    "gn:admin1_code":"08",
    "gn:asciiname":"Mungesi",
    "gn:country_code":"ZW",
    "gn:dem":1050,
    "gn:feature_class":"P",
    "gn:feature_code":"PPL",
    "gn:name":"Mungesi",
    "gn:population":0,
    "gn:timezone":"Africa/Harare",
    "iso:country":"ZW",
    "wof:name":"Mungesi",
    "wof:placetype":"locality"
},
  "geometry": {"coordinates":[31.53771,-19.92056],"type":"Point"}
}