{
  "type": "Feature",
  "properties": {
    "gn:admin1_code":"1.0",
    "gn:asciiname":"Juliasdale",
    "gn:country_code":"ZW",
    "gn:dem":1678,
    "gn:feature_class":"P",
    "gn:feature_code":"PPL",
    "gn:name":"Juliasdale",
    "gn:population":0,
    "gn:timezone":"Africa/Harare",
    "iso:country":"ZW",
    "name:bar_x_preferred":[
        "Juliasdale"
    ],
    "name:por_x_preferred":[
        "Juliasdale"
    ],
    "wof:name":"Juliasdale",
    "wof:placetype":"locality"
},
  "geometry": {"coordinates":[32.66084,-18.35817],"type":"Point"}
}