{
  "type": "Feature",
  "properties": {
    "gn:admin1_code":"08",
    "gn:asciiname":"Chadyeni",
    "gn:country_code":"ZW",
    "gn:dem":872,
    "gn:feature_class":"P",
    "gn:feature_code":"PPL",
    "gn:name":"Chadyeni",
    "gn:population":0,
    "gn:timezone":"Africa/Harare",
    "iso:country":"ZW",
    "wof:name":"Chadyeni",
    "wof:placetype":"locality"
},
  "geometry": {"coordinates":[31.76293,-19.82574],"type":"Point"}
}