{
  "type": "Feature",
  "properties": {
    "gn:admin1_code":"08",
    "gn:asciiname":"Ndimba",
    "gn:country_code":"ZW",
    "gn:dem":1008,
    "gn:feature_class":"P",
    "gn:feature_code":"PPL",
    "gn:name":"Ndimba",
    "gn:population":0,
    "gn:timezone":"Africa/Harare",
    "iso:country":"ZW",
    "wof:name":"Ndimba",
    "wof:placetype":"locality"
},
  "geometry": {"coordinates":[31.62507,-19.6677],"type":"Point"}
}