{
  "type": "Feature",
  "properties": {
    "gn:admin1_code":"08",
    "gn:asciiname":"Chinyati",
    "gn:country_code":"ZW",
    "gn:dem":842,
    "gn:feature_class":"P",
    "gn:feature_code":"PPL",
    "gn:name":"Chinyati",
    "gn:population":0,
    "gn:timezone":"Africa/Harare",
    "iso:country":"ZW",
    "wof:name":"Chinyati",
    "wof:placetype":"locality"
},
  "geometry": {"coordinates":[31.79803,-19.87053],"type":"Point"}
}