{
  "type": "Feature",
  "properties": {
    "gn:admin1_code":"08",
    "gn:asciiname":"Chivasa",
    "gn:country_code":"ZW",
    "gn:dem":993,
    "gn:feature_class":"P",
    "gn:feature_code":"PPL",
    "gn:name":"Chivasa",
    "gn:population":0,
    "gn:timezone":"Africa/Harare",
    "iso:country":"ZW",
    "wof:name":"Chivasa",
    "wof:placetype":"locality"
},
  "geometry": {"coordinates":[31.65604,-19.7568],"type":"Point"}
}