{
  "type": "Feature",
  "properties": {
    "gn:admin1_code":"6.0",
    "gn:asciiname":"Sipongweni",
    "gn:country_code":"ZW",
    "gn:dem":989,
    "gn:feature_class":"P",
    "gn:feature_code":"PPL",
    "gn:name":"Sipongweni",
    "gn:population":0,
    "gn:timezone":"Africa/Harare",
    "iso:country":"ZW",
    "wof:name":"Sipongweni",
    "wof:placetype":"locality"
},
  "geometry": {"coordinates":[27.71842,-19.23986],"type":"Point"}
}