{
  "type": "Feature",
  "properties": {
    "gn:admin1_code":"5.0",
    "gn:asciiname":"Matswaire",
    "gn:country_code":"ZW",
    "gn:dem":1305,
    "gn:feature_class":"P",
    "gn:feature_code":"PPL",
    "gn:name":"Matswaire",
    "gn:population":0,
    "gn:timezone":"Africa/Harare",
    "iso:country":"ZW",
    "name:und_x_variant":[
        "Nyamweda",
        "Matswaire"
    ],
    "wof:name":"Matswaire",
    "wof:placetype":"locality"
},
  "geometry": {"coordinates":[30.69796,-18.17792],"type":"Point"}
}